{"_path":"/maps/_hardware/hardware","_dir":"_hardware","_draft":false,"_partial":true,"_locale":"","title":"硬件","description":"硬件是指计算机的物理部分，包括 CPU、内存、硬盘、显卡等。","body":{"type":"root","children":[{"type":"element","tag":"h2","props":{"id":"主板"},"children":[{"type":"text","value":"主板"}]},{"type":"element","tag":"ul","props":{},"children":[{"type":"element","tag":"li","props":{},"children":[{"type":"element","tag":"strong","props":{},"children":[{"type":"text","value":"版型"}]},{"type":"text","value":"：mini-ITX（通常仅 2 内存插槽+1 PCIe x16）、micro-ATX 和 ATX。"}]},{"type":"element","tag":"li","props":{},"children":[{"type":"element","tag":"strong","props":{},"children":[{"type":"text","value":"命名规则"}]},{"type":"text","value":"：通常为“品牌（大系列）+芯片组（版型）+品牌系列（子系列）+后缀（如 WIFI、AX）”。"}]},{"type":"element","tag":"li","props":{},"children":[{"type":"element","tag":"strong","props":{},"children":[{"type":"text","value":"芯片组分级"}]},{"type":"text","value":"：Intel 分为 X、Z、B、H 等系列，AMD 分为 X、B、A 等系列。"}]},{"type":"element","tag":"li","props":{},"children":[{"type":"element","tag":"strong","props":{},"children":[{"type":"text","value":"主要插槽与接口"}]},{"type":"text","value":"：CPU 插槽（Intel LGA1700、AMD AM5）、PCIe 插槽、M.2 接口（替换 mSATA）、SATA 接口等。"}]},{"type":"element","tag":"li","props":{},"children":[{"type":"element","tag":"strong","props":{},"children":[{"type":"text","value":"供电接口"}]},{"type":"text","value":"：ATX、ATX_12V 等。"}]}]},{"type":"element","tag":"p","props":{},"children":[{"type":"text","value":"见："},{"type":"element","tag":"a","props":{"href":"https://www.bilibili.com/video/BV1xQ4y1b7JS/","rel":["nofollow"]},"children":[{"type":"text","value":"《【硬核科普】从零开始认识主板》"}]},{"type":"text","value":"、"},{"type":"element","tag":"a","props":{"href":"https://sspai.com/post/78672","rel":["nofollow"]},"children":[{"type":"text","value":"《手把手教你认识主板》"}]}]},{"type":"element","tag":"h2","props":{"id":"gpu"},"children":[{"type":"text","value":"GPU"}]},{"type":"element","tag":"ul","props":{},"children":[{"type":"element","tag":"li","props":{},"children":[{"type":"element","tag":"a","props":{"href":"https://segmentfault.com/a/1190000044183341","rel":["nofollow"]},"children":[{"type":"text","value":"聊透 GPU 通信技术——GPU Direct、NVLink、RDMA"}]}]}]},{"type":"element","tag":"h2","props":{"id":"存储"},"children":[{"type":"text","value":"存储"}]},{"type":"element","tag":"ul","props":{},"children":[{"type":"element","tag":"li","props":{},"children":[{"type":"element","tag":"a","props":{"href":"/maps/_hardware/ssd"},"children":[{"type":"text","value":"SSD"}]}]}]}],"toc":{"title":"","searchDepth":2,"depth":2,"links":[{"id":"主板","depth":2,"text":"主板"},{"id":"gpu","depth":2,"text":"GPU"},{"id":"存储","depth":2,"text":"存储"}]}},"_type":"markdown","_id":"content:6.maps:_hardware:hardware.md","_source":"content","_file":"6.maps/_hardware/hardware.md","_stem":"6.maps/_hardware/hardware","_extension":"md"}