{"_path":"/source-code/_es/array-slice","_dir":"_es","_draft":false,"_partial":true,"_locale":"","title":"Array.prototype.slice","description":"","body":{"type":"root","children":[{"type":"element","tag":"h2","props":{"id":"简介"},"children":[{"type":"text","value":"简介"}]},{"type":"element","tag":"p","props":{},"children":[{"type":"text","value":"Array.prototype.slice 是一个数组/类数组浅拷贝的方法，可以转化任何符合条件的伪数组宿主对象为数组，但是 IE<9 除外。"}]},{"type":"element","tag":"p","props":{},"children":[{"type":"text","value":"许多类库的数组拷贝方法都是通过 Array.prototype.slice 完成的，它们在一定程度上划分为两种阵营："}]},{"type":"element","tag":"ol","props":{},"children":[{"type":"element","tag":"li","props":{},"children":[{"type":"text","value":"拷贝数组时对 IE 浏览器特殊处理"}]},{"type":"element","tag":"li","props":{},"children":[{"type":"text","value":"当位于 IE 浏览器时，对 Array.prototype.slice 做兼容"}]}]},{"type":"element","tag":"h2","props":{"id":"特殊处理方案"},"children":[{"type":"text","value":"特殊处理方案"}]},{"type":"element","tag":"p","props":{},"children":[{"type":"text","value":"Mootools 属于第一种方案。"}]},{"type":"element","tag":"pre","props":{"className":"language-js shiki shiki-themes material-theme-lighter github-light github-dark monokai","code":"function $A(iterable) {\n    if (iterable.item) {\n        var l = iterable.length, array = new Array(l)\n        while (l--) {\n            array[l] = iterable[l]\n        }\n        return array\n    }\n    return Array.prototype.slice.call(iterable)\n}\n","language":"js","meta":"","style":""},"children":[{"type":"element","tag":"code","props":{"__ignoreMap":""},"children":[{"type":"element","tag":"span","props":{"class":"line","line":1},"children":[{"type":"element","tag":"span","props":{"style":"--shiki-light:#9C3EDA;--shiki-default:#D73A49;--shiki-dark:#F97583;--shiki-sepia:#66D9EF;--shiki-light-font-style:inherit;--shiki-default-font-style:inherit;--shiki-dark-font-style:inherit;--shiki-sepia-font-style:italic"},"children":[{"type":"text","value":"function"}]},{"type":"element","tag":"span","props":{"style":"--shiki-light:#6182B8;--shiki-default:#6F42C1;--shiki-dark:#B392F0;--shiki-sepia:#A6E22E"},"children":[{"type":"text","value":" $A"}]},{"type":"element","tag":"span","props":{"style":"--shiki-light:#39ADB5;--shiki-default:#24292E;--shiki-dark:#E1E4E8;--shiki-sepia:#F8F8F2"},"children":[{"type":"text","value":"("}]},{"type":"element","tag":"span","props":{"style":"--shiki-light:#90A4AE;--shiki-default:#E36209;--shiki-dark:#FFAB70;--shiki-sepia:#FD971F;--shiki-light-font-style:italic;--shiki-default-font-style:inherit;--shiki-dark-font-style:inherit;--shiki-sepia-font-style:italic"},"children":[{"type":"text","value":"iterable"}]},{"type":"element","tag":"span","props":{"style":"--shiki-light:#39ADB5;--shiki-default:#24292E;--shiki-dark:#E1E4E8;--shiki-sepia:#F8F8F2"},"children":[{"type":"text","value":")"}]},{"type":"element","tag":"span","props":{"style":"--shiki-light:#39ADB5;--shiki-default:#24292E;--shiki-dark:#E1E4E8;--shiki-sepia:#F8F8F2"},"children":[{"type":"text","value":" {\n"}]}]},{"type":"element","tag":"span","props":{"class":"line","line":2},"children":[{"type":"element","tag":"span","props":{"style":"--shiki-light:#39ADB5;--shiki-default:#D73A49;--shiki-dark:#F97583;--shiki-sepia:#F92672;--shiki-light-font-style:italic;--shiki-default-font-style:inherit;--shiki-dark-font-style:inherit;--shiki-sepia-font-style:inherit"},"children":[{"type":"text","value":"    if"}]},{"type":"element","tag":"span","props":{"style":"--shiki-light:#E53935;--shiki-default:#24292E;--shiki-dark:#E1E4E8;--shiki-sepia:#F8F8F2"},"children":[{"type":"text","value":" ("}]},{"type":"element","tag":"span","props":{"style":"--shiki-light:#90A4AE;--shiki-default:#24292E;--shiki-dark:#E1E4E8;--shiki-sepia:#F8F8F2"},"children":[{"type":"text","value":"iterable"}]},{"type":"element","tag":"span","props":{"style":"--shiki-light:#39ADB5;--shiki-default:#24292E;--shiki-dark:#E1E4E8;--shiki-sepia:#F8F8F2"},"children":[{"type":"text","value":"."}]},{"type":"element","tag":"span","props":{"style":"--shiki-light:#90A4AE;--shiki-default:#24292E;--shiki-dark:#E1E4E8;--shiki-sepia:#F8F8F2"},"children":[{"type":"text","value":"item"}]},{"type":"element","tag":"span","props":{"style":"--shiki-light:#E53935;--shiki-default:#24292E;--shiki-dark:#E1E4E8;--shiki-sepia:#F8F8F2"},"children":[{"type":"text","value":") "}]},{"type":"element","tag":"span","props":{"style":"--shiki-light:#39ADB5;--shiki-default:#24292E;--shiki-dark:#E1E4E8;--shiki-sepia:#F8F8F2"},"children":[{"type":"text","value":"{\n"}]}]},{"type":"element","tag":"span","props":{"class":"line","line":3},"children":[{"type":"element","tag":"span","props":{"style":"--shiki-light:#9C3EDA;--shiki-default:#D73A49;--shiki-dark:#F97583;--shiki-sepia:#66D9EF;--shiki-light-font-style:inherit;--shiki-default-font-style:inherit;--shiki-dark-font-style:inherit;--shiki-sepia-font-style:italic"},"children":[{"type":"text","value":"        var"}]},{"type":"element","tag":"span","props":{"style":"--shiki-light:#90A4AE;--shiki-default:#24292E;--shiki-dark:#E1E4E8;--shiki-sepia:#F8F8F2"},"children":[{"type":"text","value":" l"}]},{"type":"element","tag":"span","props":{"style":"--shiki-light:#39ADB5;--shiki-default:#D73A49;--shiki-dark:#F97583;--shiki-sepia:#F92672"},"children":[{"type":"text","value":" ="}]},{"type":"element","tag":"span","props":{"style":"--shiki-light:#90A4AE;--shiki-default:#24292E;--shiki-dark:#E1E4E8;--shiki-sepia:#F8F8F2"},"children":[{"type":"text","value":" iterable"}]},{"type":"element","tag":"span","props":{"style":"--shiki-light:#39ADB5;--shiki-default:#24292E;--shiki-dark:#E1E4E8;--shiki-sepia:#F8F8F2"},"children":[{"type":"text","value":"."}]},{"type":"element","tag":"span","props":{"style":"--shiki-light:#90A4AE;--shiki-default:#005CC5;--shiki-dark:#79B8FF;--shiki-sepia:#F8F8F2"},"children":[{"type":"text","value":"length"}]},{"type":"element","tag":"span","props":{"style":"--shiki-light:#39ADB5;--shiki-default:#24292E;--shiki-dark:#E1E4E8;--shiki-sepia:#F8F8F2"},"children":[{"type":"text","value":","}]},{"type":"element","tag":"span","props":{"style":"--shiki-light:#90A4AE;--shiki-default:#24292E;--shiki-dark:#E1E4E8;--shiki-sepia:#F8F8F2"},"children":[{"type":"text","value":" array"}]},{"type":"element","tag":"span","props":{"style":"--shiki-light:#39ADB5;--shiki-default:#D73A49;--shiki-dark:#F97583;--shiki-sepia:#F92672"},"children":[{"type":"text","value":" ="}]},{"type":"element","tag":"span","props":{"style":"--shiki-light:#39ADB5;--shiki-default:#D73A49;--shiki-dark:#F97583;--shiki-sepia:#F92672"},"children":[{"type":"text","value":" new"}]},{"type":"element","tag":"span","props":{"style":"--shiki-light:#6182B8;--shiki-default:#6F42C1;--shiki-dark:#B392F0;--shiki-sepia:#A6E22E"},"children":[{"type":"text","value":" Array"}]},{"type":"element","tag":"span","props":{"style":"--shiki-light:#E53935;--shiki-default:#24292E;--shiki-dark:#E1E4E8;--shiki-sepia:#F8F8F2"},"children":[{"type":"text","value":"("}]},{"type":"element","tag":"span","props":{"style":"--shiki-light:#90A4AE;--shiki-default:#24292E;--shiki-dark:#E1E4E8;--shiki-sepia:#F8F8F2"},"children":[{"type":"text","value":"l"}]},{"type":"element","tag":"span","props":{"style":"--shiki-light:#E53935;--shiki-default:#24292E;--shiki-dark:#E1E4E8;--shiki-sepia:#F8F8F2"},"children":[{"type":"text","value":")\n"}]}]},{"type":"element","tag":"span","props":{"class":"line","line":4},"children":[{"type":"element","tag":"span","props":{"style":"--shiki-light:#39ADB5;--shiki-default:#D73A49;--shiki-dark:#F97583;--shiki-sepia:#F92672;--shiki-light-font-style:italic;--shiki-default-font-style:inherit;--shiki-dark-font-style:inherit;--shiki-sepia-font-style:inherit"},"children":[{"type":"text","value":"        while"}]},{"type":"element","tag":"span","props":{"style":"--shiki-light:#E53935;--shiki-default:#24292E;--shiki-dark:#E1E4E8;--shiki-sepia:#F8F8F2"},"children":[{"type":"text","value":" ("}]},{"type":"element","tag":"span","props":{"style":"--shiki-light:#90A4AE;--shiki-default:#24292E;--shiki-dark:#E1E4E8;--shiki-sepia:#F8F8F2"},"children":[{"type":"text","value":"l"}]},{"type":"element","tag":"span","props":{"style":"--shiki-light:#39ADB5;--shiki-default:#D73A49;--shiki-dark:#F97583;--shiki-sepia:#F92672"},"children":[{"type":"text","value":"--"}]},{"type":"element","tag":"span","props":{"style":"--shiki-light:#E53935;--shiki-default:#24292E;--shiki-dark:#E1E4E8;--shiki-sepia:#F8F8F2"},"children":[{"type":"text","value":") "}]},{"type":"element","tag":"span","props":{"style":"--shiki-light:#39ADB5;--shiki-default:#24292E;--shiki-dark:#E1E4E8;--shiki-sepia:#F8F8F2"},"children":[{"type":"text","value":"{\n"}]}]},{"type":"element","tag":"span","props":{"class":"line","line":5},"children":[{"type":"element","tag":"span","props":{"style":"--shiki-light:#90A4AE;--shiki-default:#24292E;--shiki-dark:#E1E4E8;--shiki-sepia:#F8F8F2"},"children":[{"type":"text","value":"            array"}]},{"type":"element","tag":"span","props":{"style":"--shiki-light:#E53935;--shiki-default:#24292E;--shiki-dark:#E1E4E8;--shiki-sepia:#F8F8F2"},"children":[{"type":"text","value":"["}]},{"type":"element","tag":"span","props":{"style":"--shiki-light:#90A4AE;--shiki-default:#24292E;--shiki-dark:#E1E4E8;--shiki-sepia:#F8F8F2"},"children":[{"type":"text","value":"l"}]},{"type":"element","tag":"span","props":{"style":"--shiki-light:#E53935;--shiki-default:#24292E;--shiki-dark:#E1E4E8;--shiki-sepia:#F8F8F2"},"children":[{"type":"text","value":"] "}]},{"type":"element","tag":"span","props":{"style":"--shiki-light:#39ADB5;--shiki-default:#D73A49;--shiki-dark:#F97583;--shiki-sepia:#F92672"},"children":[{"type":"text","value":"="}]},{"type":"element","tag":"span","props":{"style":"--shiki-light:#90A4AE;--shiki-default:#24292E;--shiki-dark:#E1E4E8;--shiki-sepia:#F8F8F2"},"children":[{"type":"text","value":" iterable"}]},{"type":"element","tag":"span","props":{"style":"--shiki-light:#E53935;--shiki-default:#24292E;--shiki-dark:#E1E4E8;--shiki-sepia:#F8F8F2"},"children":[{"type":"text","value":"["}]},{"type":"element","tag":"span","props":{"style":"--shiki-light:#90A4AE;--shiki-default:#24292E;--shiki-dark:#E1E4E8;--shiki-sepia:#F8F8F2"},"children":[{"type":"text","value":"l"}]},{"type":"element","tag":"span","props":{"style":"--shiki-light:#E53935;--shiki-default:#24292E;--shiki-dark:#E1E4E8;--shiki-sepia:#F8F8F2"},"children":[{"type":"text","value":"]\n"}]}]},{"type":"element","tag":"span","props":{"class":"line","line":6},"children":[{"type":"element","tag":"span","props":{"style":"--shiki-light:#39ADB5;--shiki-default:#24292E;--shiki-dark:#E1E4E8;--shiki-sepia:#F8F8F2"},"children":[{"type":"text","value":"        }\n"}]}]},{"type":"element","tag":"span","props":{"class":"line","line":7},"children":[{"type":"element","tag":"span","props":{"style":"--shiki-light:#39ADB5;--shiki-default:#D73A49;--shiki-dark:#F97583;--shiki-sepia:#F92672;--shiki-light-font-style:italic;--shiki-default-font-style:inherit;--shiki-dark-font-style:inherit;--shiki-sepia-font-style:inherit"},"children":[{"type":"text","value":"        return"}]},{"type":"element","tag":"span","props":{"style":"--shiki-light:#90A4AE;--shiki-default:#24292E;--shiki-dark:#E1E4E8;--shiki-sepia:#F8F8F2"},"children":[{"type":"text","value":" array\n"}]}]},{"type":"element","tag":"span","props":{"class":"line","line":8},"children":[{"type":"element","tag":"span","props":{"style":"--shiki-light:#39ADB5;--shiki-default:#24292E;--shiki-dark:#E1E4E8;--shiki-sepia:#F8F8F2"},"children":[{"type":"text","value":"    }\n"}]}]},{"type":"element","tag":"span","props":{"class":"line","line":9},"children":[{"type":"element","tag":"span","props":{"style":"--shiki-light:#39ADB5;--shiki-default:#D73A49;--shiki-dark:#F97583;--shiki-sepia:#F92672;--shiki-light-font-style:italic;--shiki-default-font-style:inherit;--shiki-dark-font-style:inherit;--shiki-sepia-font-style:inherit"},"children":[{"type":"text","value":"    return"}]},{"type":"element","tag":"span","props":{"style":"--shiki-light:#E2931D;--shiki-default:#005CC5;--shiki-dark:#79B8FF;--shiki-sepia:#66D9EF;--shiki-light-font-style:inherit;--shiki-default-font-style:inherit;--shiki-dark-font-style:inherit;--shiki-sepia-font-style:italic"},"children":[{"type":"text","value":" Array"}]},{"type":"element","tag":"span","props":{"style":"--shiki-light:#39ADB5;--shiki-default:#24292E;--shiki-dark:#E1E4E8;--shiki-sepia:#F8F8F2"},"children":[{"type":"text","value":"."}]},{"type":"element","tag":"span","props":{"style":"--shiki-light:#90A4AE;--shiki-default:#005CC5;--shiki-dark:#79B8FF;--shiki-sepia:#F8F8F2"},"children":[{"type":"text","value":"prototype"}]},{"type":"element","tag":"span","props":{"style":"--shiki-light:#39ADB5;--shiki-default:#24292E;--shiki-dark:#E1E4E8;--shiki-sepia:#F8F8F2"},"children":[{"type":"text","value":"."}]},{"type":"element","tag":"span","props":{"style":"--shiki-light:#90A4AE;--shiki-default:#24292E;--shiki-dark:#E1E4E8;--shiki-sepia:#F8F8F2"},"children":[{"type":"text","value":"slice"}]},{"type":"element","tag":"span","props":{"style":"--shiki-light:#39ADB5;--shiki-default:#24292E;--shiki-dark:#E1E4E8;--shiki-sepia:#F8F8F2"},"children":[{"type":"text","value":"."}]},{"type":"element","tag":"span","props":{"style":"--shiki-light:#6182B8;--shiki-default:#6F42C1;--shiki-dark:#B392F0;--shiki-sepia:#A6E22E"},"children":[{"type":"text","value":"call"}]},{"type":"element","tag":"span","props":{"style":"--shiki-light:#E53935;--shiki-default:#24292E;--shiki-dark:#E1E4E8;--shiki-sepia:#F8F8F2"},"children":[{"type":"text","value":"("}]},{"type":"element","tag":"span","props":{"style":"--shiki-light:#90A4AE;--shiki-default:#24292E;--shiki-dark:#E1E4E8;--shiki-sepia:#F8F8F2"},"children":[{"type":"text","value":"iterable"}]},{"type":"element","tag":"span","props":{"style":"--shiki-light:#E53935;--shiki-default:#24292E;--shiki-dark:#E1E4E8;--shiki-sepia:#F8F8F2"},"children":[{"type":"text","value":")\n"}]}]},{"type":"element","tag":"span","props":{"class":"line","line":10},"children":[{"type":"element","tag":"span","props":{"style":"--shiki-light:#39ADB5;--shiki-default:#24292E;--shiki-dark:#E1E4E8;--shiki-sepia:#F8F8F2"},"children":[{"type":"text","value":"}\n"}]}]}]}]},{"type":"element","tag":"p","props":{},"children":[{"type":"text","value":"Ext 也属于第一种方案。"}]},{"type":"element","tag":"pre","props":{"className":"language-js shiki shiki-themes material-theme-lighter github-light github-dark monokai","code":"var toArray = function toArray() {\n    return isIE\n        ? function(a, i, j, res) {\n            res = []\n            Ext.each(a, function (v) {\n                res.push(v)\n            })\n            return res.slice(i || 0, j || res.length)\n        }\n        : function(a, i, j) {\n            return Array.prototype.slice.call(a, i || 0, j || a.length)\n        }\n}()\n","language":"js","meta":"","style":""},"children":[{"type":"element","tag":"code","props":{"__ignoreMap":""},"children":[{"type":"element","tag":"span","props":{"class":"line","line":1},"children":[{"type":"element","tag":"span","props":{"style":"--shiki-light:#9C3EDA;--shiki-default:#D73A49;--shiki-dark:#F97583;--shiki-sepia:#66D9EF;--shiki-light-font-style:inherit;--shiki-default-font-style:inherit;--shiki-dark-font-style:inherit;--shiki-sepia-font-style:italic"},"children":[{"type":"text","value":"var"}]},{"type":"element","tag":"span","props":{"style":"--shiki-light:#90A4AE;--shiki-default:#6F42C1;--shiki-dark:#B392F0;--shiki-sepia:#A6E22E"},"children":[{"type":"text","value":" toArray"}]},{"type":"element","tag":"span","props":{"style":"--shiki-light:#39ADB5;--shiki-default:#D73A49;--shiki-dark:#F97583;--shiki-sepia:#F92672"},"children":[{"type":"text","value":" ="}]},{"type":"element","tag":"span","props":{"style":"--shiki-light:#9C3EDA;--shiki-default:#D73A49;--shiki-dark:#F97583;--shiki-sepia:#66D9EF;--shiki-light-font-style:inherit;--shiki-default-font-style:inherit;--shiki-dark-font-style:inherit;--shiki-sepia-font-style:italic"},"children":[{"type":"text","value":" function"}]},{"type":"element","tag":"span","props":{"style":"--shiki-light:#6182B8;--shiki-default:#6F42C1;--shiki-dark:#B392F0;--shiki-sepia:#A6E22E"},"children":[{"type":"text","value":" toArray"}]},{"type":"element","tag":"span","props":{"style":"--shiki-light:#39ADB5;--shiki-default:#24292E;--shiki-dark:#E1E4E8;--shiki-sepia:#F8F8F2"},"children":[{"type":"text","value":"()"}]},{"type":"element","tag":"span","props":{"style":"--shiki-light:#39ADB5;--shiki-default:#24292E;--shiki-dark:#E1E4E8;--shiki-sepia:#F8F8F2"},"children":[{"type":"text","value":" {\n"}]}]},{"type":"element","tag":"span","props":{"class":"line","line":2},"children":[{"type":"element","tag":"span","props":{"style":"--shiki-light:#39ADB5;--shiki-default:#D73A49;--shiki-dark:#F97583;--shiki-sepia:#F92672;--shiki-light-font-style:italic;--shiki-default-font-style:inherit;--shiki-dark-font-style:inherit;--shiki-sepia-font-style:inherit"},"children":[{"type":"text","value":"    return"}]},{"type":"element","tag":"span","props":{"style":"--shiki-light:#90A4AE;--shiki-default:#24292E;--shiki-dark:#E1E4E8;--shiki-sepia:#F8F8F2"},"children":[{"type":"text","value":" isIE\n"}]}]},{"type":"element","tag":"span","props":{"class":"line","line":3},"children":[{"type":"element","tag":"span","props":{"style":"--shiki-light:#39ADB5;--shiki-default:#D73A49;--shiki-dark:#F97583;--shiki-sepia:#F92672"},"children":[{"type":"text","value":"        ?"}]},{"type":"element","tag":"span","props":{"style":"--shiki-light:#9C3EDA;--shiki-default:#D73A49;--shiki-dark:#F97583;--shiki-sepia:#66D9EF;--shiki-light-font-style:inherit;--shiki-default-font-style:inherit;--shiki-dark-font-style:inherit;--shiki-sepia-font-style:italic"},"children":[{"type":"text","value":" function"}]},{"type":"element","tag":"span","props":{"style":"--shiki-light:#39ADB5;--shiki-default:#24292E;--shiki-dark:#E1E4E8;--shiki-sepia:#F8F8F2"},"children":[{"type":"text","value":"("}]},{"type":"element","tag":"span","props":{"style":"--shiki-light:#90A4AE;--shiki-default:#E36209;--shiki-dark:#FFAB70;--shiki-sepia:#FD971F;--shiki-light-font-style:italic;--shiki-default-font-style:inherit;--shiki-dark-font-style:inherit;--shiki-sepia-font-style:italic"},"children":[{"type":"text","value":"a"}]},{"type":"element","tag":"span","props":{"style":"--shiki-light:#39ADB5;--shiki-default:#24292E;--shiki-dark:#E1E4E8;--shiki-sepia:#F8F8F2"},"children":[{"type":"text","value":","}]},{"type":"element","tag":"span","props":{"style":"--shiki-light:#90A4AE;--shiki-default:#E36209;--shiki-dark:#FFAB70;--shiki-sepia:#FD971F;--shiki-light-font-style:italic;--shiki-default-font-style:inherit;--shiki-dark-font-style:inherit;--shiki-sepia-font-style:italic"},"children":[{"type":"text","value":" i"}]},{"type":"element","tag":"span","props":{"style":"--shiki-light:#39ADB5;--shiki-default:#24292E;--shiki-dark:#E1E4E8;--shiki-sepia:#F8F8F2"},"children":[{"type":"text","value":","}]},{"type":"element","tag":"span","props":{"style":"--shiki-light:#90A4AE;--shiki-default:#E36209;--shiki-dark:#FFAB70;--shiki-sepia:#FD971F;--shiki-light-font-style:italic;--shiki-default-font-style:inherit;--shiki-dark-font-style:inherit;--shiki-sepia-font-style:italic"},"children":[{"type":"text","value":" j"}]},{"type":"element","tag":"span","props":{"style":"--shiki-light:#39ADB5;--shiki-default:#24292E;--shiki-dark:#E1E4E8;--shiki-sepia:#F8F8F2"},"children":[{"type":"text","value":","}]},{"type":"element","tag":"span","props":{"style":"--shiki-light:#90A4AE;--shiki-default:#E36209;--shiki-dark:#FFAB70;--shiki-sepia:#FD971F;--shiki-light-font-style:italic;--shiki-default-font-style:inherit;--shiki-dark-font-style:inherit;--shiki-sepia-font-style:italic"},"children":[{"type":"text","value":" res"}]},{"type":"element","tag":"span","props":{"style":"--shiki-light:#39ADB5;--shiki-default:#24292E;--shiki-dark:#E1E4E8;--shiki-sepia:#F8F8F2"},"children":[{"type":"text","value":")"}]},{"type":"element","tag":"span","props":{"style":"--shiki-light:#39ADB5;--shiki-default:#24292E;--shiki-dark:#E1E4E8;--shiki-sepia:#F8F8F2"},"children":[{"type":"text","value":" {\n"}]}]},{"type":"element","tag":"span","props":{"class":"line","line":4},"children":[{"type":"element","tag":"span","props":{"style":"--shiki-light:#90A4AE;--shiki-default:#24292E;--shiki-dark:#E1E4E8;--shiki-sepia:#F8F8F2"},"children":[{"type":"text","value":"            res"}]},{"type":"element","tag":"span","props":{"style":"--shiki-light:#39ADB5;--shiki-default:#D73A49;--shiki-dark:#F97583;--shiki-sepia:#F92672"},"children":[{"type":"text","value":" ="}]},{"type":"element","tag":"span","props":{"style":"--shiki-light:#E53935;--shiki-default:#24292E;--shiki-dark:#E1E4E8;--shiki-sepia:#F8F8F2"},"children":[{"type":"text","value":" []\n"}]}]},{"type":"element","tag":"span","props":{"class":"line","line":5},"children":[{"type":"element","tag":"span","props":{"style":"--shiki-light:#90A4AE;--shiki-default:#24292E;--shiki-dark:#E1E4E8;--shiki-sepia:#F8F8F2"},"children":[{"type":"text","value":"            Ext"}]},{"type":"element","tag":"span","props":{"style":"--shiki-light:#39ADB5;--shiki-default:#24292E;--shiki-dark:#E1E4E8;--shiki-sepia:#F8F8F2"},"children":[{"type":"text","value":"."}]},{"type":"element","tag":"span","props":{"style":"--shiki-light:#6182B8;--shiki-default:#6F42C1;--shiki-dark:#B392F0;--shiki-sepia:#A6E22E"},"children":[{"type":"text","value":"each"}]},{"type":"element","tag":"span","props":{"style":"--shiki-light:#E53935;--shiki-default:#24292E;--shiki-dark:#E1E4E8;--shiki-sepia:#F8F8F2"},"children":[{"type":"text","value":"("}]},{"type":"element","tag":"span","props":{"style":"--shiki-light:#90A4AE;--shiki-default:#24292E;--shiki-dark:#E1E4E8;--shiki-sepia:#F8F8F2"},"children":[{"type":"text","value":"a"}]},{"type":"element","tag":"span","props":{"style":"--shiki-light:#39ADB5;--shiki-default:#24292E;--shiki-dark:#E1E4E8;--shiki-sepia:#F8F8F2"},"children":[{"type":"text","value":","}]},{"type":"element","tag":"span","props":{"style":"--shiki-light:#9C3EDA;--shiki-default:#D73A49;--shiki-dark:#F97583;--shiki-sepia:#66D9EF;--shiki-light-font-style:inherit;--shiki-default-font-style:inherit;--shiki-dark-font-style:inherit;--shiki-sepia-font-style:italic"},"children":[{"type":"text","value":" function"}]},{"type":"element","tag":"span","props":{"style":"--shiki-light:#39ADB5;--shiki-default:#24292E;--shiki-dark:#E1E4E8;--shiki-sepia:#F8F8F2"},"children":[{"type":"text","value":" ("}]},{"type":"element","tag":"span","props":{"style":"--shiki-light:#90A4AE;--shiki-default:#E36209;--shiki-dark:#FFAB70;--shiki-sepia:#FD971F;--shiki-light-font-style:italic;--shiki-default-font-style:inherit;--shiki-dark-font-style:inherit;--shiki-sepia-font-style:italic"},"children":[{"type":"text","value":"v"}]},{"type":"element","tag":"span","props":{"style":"--shiki-light:#39ADB5;--shiki-default:#24292E;--shiki-dark:#E1E4E8;--shiki-sepia:#F8F8F2"},"children":[{"type":"text","value":")"}]},{"type":"element","tag":"span","props":{"style":"--shiki-light:#39ADB5;--shiki-default:#24292E;--shiki-dark:#E1E4E8;--shiki-sepia:#F8F8F2"},"children":[{"type":"text","value":" {\n"}]}]},{"type":"element","tag":"span","props":{"class":"line","line":6},"children":[{"type":"element","tag":"span","props":{"style":"--shiki-light:#90A4AE;--shiki-default:#24292E;--shiki-dark:#E1E4E8;--shiki-sepia:#F8F8F2"},"children":[{"type":"text","value":"                res"}]},{"type":"element","tag":"span","props":{"style":"--shiki-light:#39ADB5;--shiki-default:#24292E;--shiki-dark:#E1E4E8;--shiki-sepia:#F8F8F2"},"children":[{"type":"text","value":"."}]},{"type":"element","tag":"span","props":{"style":"--shiki-light:#6182B8;--shiki-default:#6F42C1;--shiki-dark:#B392F0;--shiki-sepia:#A6E22E"},"children":[{"type":"text","value":"push"}]},{"type":"element","tag":"span","props":{"style":"--shiki-light:#E53935;--shiki-default:#24292E;--shiki-dark:#E1E4E8;--shiki-sepia:#F8F8F2"},"children":[{"type":"text","value":"("}]},{"type":"element","tag":"span","props":{"style":"--shiki-light:#90A4AE;--shiki-default:#24292E;--shiki-dark:#E1E4E8;--shiki-sepia:#F8F8F2"},"children":[{"type":"text","value":"v"}]},{"type":"element","tag":"span","props":{"style":"--shiki-light:#E53935;--shiki-default:#24292E;--shiki-dark:#E1E4E8;--shiki-sepia:#F8F8F2"},"children":[{"type":"text","value":")\n"}]}]},{"type":"element","tag":"span","props":{"class":"line","line":7},"children":[{"type":"element","tag":"span","props":{"style":"--shiki-light:#39ADB5;--shiki-default:#24292E;--shiki-dark:#E1E4E8;--shiki-sepia:#F8F8F2"},"children":[{"type":"text","value":"            }"}]},{"type":"element","tag":"span","props":{"style":"--shiki-light:#E53935;--shiki-default:#24292E;--shiki-dark:#E1E4E8;--shiki-sepia:#F8F8F2"},"children":[{"type":"text","value":")\n"}]}]},{"type":"element","tag":"span","props":{"class":"line","line":8},"children":[{"type":"element","tag":"span","props":{"style":"--shiki-light:#39ADB5;--shiki-default:#D73A49;--shiki-dark:#F97583;--shiki-sepia:#F92672;--shiki-light-font-style:italic;--shiki-default-font-style:inherit;--shiki-dark-font-style:inherit;--shiki-sepia-font-style:inherit"},"children":[{"type":"text","value":"            return"}]},{"type":"element","tag":"span","props":{"style":"--shiki-light:#90A4AE;--shiki-default:#24292E;--shiki-dark:#E1E4E8;--shiki-sepia:#F8F8F2"},"children":[{"type":"text","value":" res"}]},{"type":"element","tag":"span","props":{"style":"--shiki-light:#39ADB5;--shiki-default:#24292E;--shiki-dark:#E1E4E8;--shiki-sepia:#F8F8F2"},"children":[{"type":"text","value":"."}]},{"type":"element","tag":"span","props":{"style":"--shiki-light:#6182B8;--shiki-default:#6F42C1;--shiki-dark:#B392F0;--shiki-sepia:#A6E22E"},"children":[{"type":"text","value":"slice"}]},{"type":"element","tag":"span","props":{"style":"--shiki-light:#E53935;--shiki-default:#24292E;--shiki-dark:#E1E4E8;--shiki-sepia:#F8F8F2"},"children":[{"type":"text","value":"("}]},{"type":"element","tag":"span","props":{"style":"--shiki-light:#90A4AE;--shiki-default:#24292E;--shiki-dark:#E1E4E8;--shiki-sepia:#F8F8F2"},"children":[{"type":"text","value":"i"}]},{"type":"element","tag":"span","props":{"style":"--shiki-light:#39ADB5;--shiki-default:#D73A49;--shiki-dark:#F97583;--shiki-sepia:#F92672"},"children":[{"type":"text","value":" ||"}]},{"type":"element","tag":"span","props":{"style":"--shiki-light:#F76D47;--shiki-default:#005CC5;--shiki-dark:#79B8FF;--shiki-sepia:#AE81FF"},"children":[{"type":"text","value":" 0"}]},{"type":"element","tag":"span","props":{"style":"--shiki-light:#39ADB5;--shiki-default:#24292E;--shiki-dark:#E1E4E8;--shiki-sepia:#F8F8F2"},"children":[{"type":"text","value":","}]},{"type":"element","tag":"span","props":{"style":"--shiki-light:#90A4AE;--shiki-default:#24292E;--shiki-dark:#E1E4E8;--shiki-sepia:#F8F8F2"},"children":[{"type":"text","value":" j"}]},{"type":"element","tag":"span","props":{"style":"--shiki-light:#39ADB5;--shiki-default:#D73A49;--shiki-dark:#F97583;--shiki-sepia:#F92672"},"children":[{"type":"text","value":" ||"}]},{"type":"element","tag":"span","props":{"style":"--shiki-light:#90A4AE;--shiki-default:#24292E;--shiki-dark:#E1E4E8;--shiki-sepia:#F8F8F2"},"children":[{"type":"text","value":" res"}]},{"type":"element","tag":"span","props":{"style":"--shiki-light:#39ADB5;--shiki-default:#24292E;--shiki-dark:#E1E4E8;--shiki-sepia:#F8F8F2"},"children":[{"type":"text","value":"."}]},{"type":"element","tag":"span","props":{"style":"--shiki-light:#90A4AE;--shiki-default:#005CC5;--shiki-dark:#79B8FF;--shiki-sepia:#F8F8F2"},"children":[{"type":"text","value":"length"}]},{"type":"element","tag":"span","props":{"style":"--shiki-light:#E53935;--shiki-default:#24292E;--shiki-dark:#E1E4E8;--shiki-sepia:#F8F8F2"},"children":[{"type":"text","value":")\n"}]}]},{"type":"element","tag":"span","props":{"class":"line","line":9},"children":[{"type":"element","tag":"span","props":{"style":"--shiki-light:#39ADB5;--shiki-default:#24292E;--shiki-dark:#E1E4E8;--shiki-sepia:#F8F8F2"},"children":[{"type":"text","value":"        }\n"}]}]},{"type":"element","tag":"span","props":{"class":"line","line":10},"children":[{"type":"element","tag":"span","props":{"style":"--shiki-light:#39ADB5;--shiki-default:#D73A49;--shiki-dark:#F97583;--shiki-sepia:#F92672"},"children":[{"type":"text","value":"        :"}]},{"type":"element","tag":"span","props":{"style":"--shiki-light:#9C3EDA;--shiki-default:#D73A49;--shiki-dark:#F97583;--shiki-sepia:#66D9EF;--shiki-light-font-style:inherit;--shiki-default-font-style:inherit;--shiki-dark-font-style:inherit;--shiki-sepia-font-style:italic"},"children":[{"type":"text","value":" function"}]},{"type":"element","tag":"span","props":{"style":"--shiki-light:#39ADB5;--shiki-default:#24292E;--shiki-dark:#E1E4E8;--shiki-sepia:#F8F8F2"},"children":[{"type":"text","value":"("}]},{"type":"element","tag":"span","props":{"style":"--shiki-light:#90A4AE;--shiki-default:#E36209;--shiki-dark:#FFAB70;--shiki-sepia:#FD971F;--shiki-light-font-style:italic;--shiki-default-font-style:inherit;--shiki-dark-font-style:inherit;--shiki-sepia-font-style:italic"},"children":[{"type":"text","value":"a"}]},{"type":"element","tag":"span","props":{"style":"--shiki-light:#39ADB5;--shiki-default:#24292E;--shiki-dark:#E1E4E8;--shiki-sepia:#F8F8F2"},"children":[{"type":"text","value":","}]},{"type":"element","tag":"span","props":{"style":"--shiki-light:#90A4AE;--shiki-default:#E36209;--shiki-dark:#FFAB70;--shiki-sepia:#FD971F;--shiki-light-font-style:italic;--shiki-default-font-style:inherit;--shiki-dark-font-style:inherit;--shiki-sepia-font-style:italic"},"children":[{"type":"text","value":" i"}]},{"type":"element","tag":"span","props":{"style":"--shiki-light:#39ADB5;--shiki-default:#24292E;--shiki-dark:#E1E4E8;--shiki-sepia:#F8F8F2"},"children":[{"type":"text","value":","}]},{"type":"element","tag":"span","props":{"style":"--shiki-light:#90A4AE;--shiki-default:#E36209;--shiki-dark:#FFAB70;--shiki-sepia:#FD971F;--shiki-light-font-style:italic;--shiki-default-font-style:inherit;--shiki-dark-font-style:inherit;--shiki-sepia-font-style:italic"},"children":[{"type":"text","value":" j"}]},{"type":"element","tag":"span","props":{"style":"--shiki-light:#39ADB5;--shiki-default:#24292E;--shiki-dark:#E1E4E8;--shiki-sepia:#F8F8F2"},"children":[{"type":"text","value":")"}]},{"type":"element","tag":"span","props":{"style":"--shiki-light:#39ADB5;--shiki-default:#24292E;--shiki-dark:#E1E4E8;--shiki-sepia:#F8F8F2"},"children":[{"type":"text","value":" {\n"}]}]},{"type":"element","tag":"span","props":{"class":"line","line":11},"children":[{"type":"element","tag":"span","props":{"style":"--shiki-light:#39ADB5;--shiki-default:#D73A49;--shiki-dark:#F97583;--shiki-sepia:#F92672;--shiki-light-font-style:italic;--shiki-default-font-style:inherit;--shiki-dark-font-style:inherit;--shiki-sepia-font-style:inherit"},"children":[{"type":"text","value":"            return"}]},{"type":"element","tag":"span","props":{"style":"--shiki-light:#E2931D;--shiki-default:#005CC5;--shiki-dark:#79B8FF;--shiki-sepia:#66D9EF;--shiki-light-font-style:inherit;--shiki-default-font-style:inherit;--shiki-dark-font-style:inherit;--shiki-sepia-font-style:italic"},"children":[{"type":"text","value":" Array"}]},{"type":"element","tag":"span","props":{"style":"--shiki-light:#39ADB5;--shiki-default:#24292E;--shiki-dark:#E1E4E8;--shiki-sepia:#F8F8F2"},"children":[{"type":"text","value":"."}]},{"type":"element","tag":"span","props":{"style":"--shiki-light:#90A4AE;--shiki-default:#005CC5;--shiki-dark:#79B8FF;--shiki-sepia:#F8F8F2"},"children":[{"type":"text","value":"prototype"}]},{"type":"element","tag":"span","props":{"style":"--shiki-light:#39ADB5;--shiki-default:#24292E;--shiki-dark:#E1E4E8;--shiki-sepia:#F8F8F2"},"children":[{"type":"text","value":"."}]},{"type":"element","tag":"span","props":{"style":"--shiki-light:#90A4AE;--shiki-default:#24292E;--shiki-dark:#E1E4E8;--shiki-sepia:#F8F8F2"},"children":[{"type":"text","value":"slice"}]},{"type":"element","tag":"span","props":{"style":"--shiki-light:#39ADB5;--shiki-default:#24292E;--shiki-dark:#E1E4E8;--shiki-sepia:#F8F8F2"},"children":[{"type":"text","value":"."}]},{"type":"element","tag":"span","props":{"style":"--shiki-light:#6182B8;--shiki-default:#6F42C1;--shiki-dark:#B392F0;--shiki-sepia:#A6E22E"},"children":[{"type":"text","value":"call"}]},{"type":"element","tag":"span","props":{"style":"--shiki-light:#E53935;--shiki-default:#24292E;--shiki-dark:#E1E4E8;--shiki-sepia:#F8F8F2"},"children":[{"type":"text","value":"("}]},{"type":"element","tag":"span","props":{"style":"--shiki-light:#90A4AE;--shiki-default:#24292E;--shiki-dark:#E1E4E8;--shiki-sepia:#F8F8F2"},"children":[{"type":"text","value":"a"}]},{"type":"element","tag":"span","props":{"style":"--shiki-light:#39ADB5;--shiki-default:#24292E;--shiki-dark:#E1E4E8;--shiki-sepia:#F8F8F2"},"children":[{"type":"text","value":","}]},{"type":"element","tag":"span","props":{"style":"--shiki-light:#90A4AE;--shiki-default:#24292E;--shiki-dark:#E1E4E8;--shiki-sepia:#F8F8F2"},"children":[{"type":"text","value":" i"}]},{"type":"element","tag":"span","props":{"style":"--shiki-light:#39ADB5;--shiki-default:#D73A49;--shiki-dark:#F97583;--shiki-sepia:#F92672"},"children":[{"type":"text","value":" ||"}]},{"type":"element","tag":"span","props":{"style":"--shiki-light:#F76D47;--shiki-default:#005CC5;--shiki-dark:#79B8FF;--shiki-sepia:#AE81FF"},"children":[{"type":"text","value":" 0"}]},{"type":"element","tag":"span","props":{"style":"--shiki-light:#39ADB5;--shiki-default:#24292E;--shiki-dark:#E1E4E8;--shiki-sepia:#F8F8F2"},"children":[{"type":"text","value":","}]},{"type":"element","tag":"span","props":{"style":"--shiki-light:#90A4AE;--shiki-default:#24292E;--shiki-dark:#E1E4E8;--shiki-sepia:#F8F8F2"},"children":[{"type":"text","value":" j"}]},{"type":"element","tag":"span","props":{"style":"--shiki-light:#39ADB5;--shiki-default:#D73A49;--shiki-dark:#F97583;--shiki-sepia:#F92672"},"children":[{"type":"text","value":" ||"}]},{"type":"element","tag":"span","props":{"style":"--shiki-light:#90A4AE;--shiki-default:#24292E;--shiki-dark:#E1E4E8;--shiki-sepia:#F8F8F2"},"children":[{"type":"text","value":" a"}]},{"type":"element","tag":"span","props":{"style":"--shiki-light:#39ADB5;--shiki-default:#24292E;--shiki-dark:#E1E4E8;--shiki-sepia:#F8F8F2"},"children":[{"type":"text","value":"."}]},{"type":"element","tag":"span","props":{"style":"--shiki-light:#90A4AE;--shiki-default:#005CC5;--shiki-dark:#79B8FF;--shiki-sepia:#F8F8F2"},"children":[{"type":"text","value":"length"}]},{"type":"element","tag":"span","props":{"style":"--shiki-light:#E53935;--shiki-default:#24292E;--shiki-dark:#E1E4E8;--shiki-sepia:#F8F8F2"},"children":[{"type":"text","value":")\n"}]}]},{"type":"element","tag":"span","props":{"class":"line","line":12},"children":[{"type":"element","tag":"span","props":{"style":"--shiki-light:#39ADB5;--shiki-default:#24292E;--shiki-dark:#E1E4E8;--shiki-sepia:#F8F8F2"},"children":[{"type":"text","value":"        }\n"}]}]},{"type":"element","tag":"span","props":{"class":"line","line":13},"children":[{"type":"element","tag":"span","props":{"style":"--shiki-light:#39ADB5;--shiki-default:#24292E;--shiki-dark:#E1E4E8;--shiki-sepia:#F8F8F2"},"children":[{"type":"text","value":"}"}]},{"type":"element","tag":"span","props":{"style":"--shiki-light:#90A4AE;--shiki-default:#24292E;--shiki-dark:#E1E4E8;--shiki-sepia:#F8F8F2"},"children":[{"type":"text","value":"()\n"}]}]}]}]},{"type":"element","tag":"h2","props":{"id":"改进-arrayprototypeslice"},"children":[{"type":"text","value":"改进 Array.prototype.slice"}]},{"type":"element","tag":"p","props":{},"children":[{"type":"text","value":"第一种方案，使得浏览器兼容与框架本身耦合性很大，司徒正美在他的著作《JS框架设计》中提到了一种改善方案，即框架本身处理数组拷贝时，只依赖 Array.prototype.slice 函数："}]},{"type":"element","tag":"pre","props":{"className":"language-js shiki shiki-themes material-theme-lighter github-light github-dark monokai","code":"Array.prototype.slice.call(something)\n","language":"js","meta":"","style":""},"children":[{"type":"element","tag":"code","props":{"__ignoreMap":""},"children":[{"type":"element","tag":"span","props":{"class":"line","line":1},"children":[{"type":"element","tag":"span","props":{"style":"--shiki-light:#E2931D;--shiki-default:#005CC5;--shiki-dark:#79B8FF;--shiki-sepia:#66D9EF;--shiki-light-font-style:inherit;--shiki-default-font-style:inherit;--shiki-dark-font-style:inherit;--shiki-sepia-font-style:italic"},"children":[{"type":"text","value":"Array"}]},{"type":"element","tag":"span","props":{"style":"--shiki-light:#39ADB5;--shiki-default:#24292E;--shiki-dark:#E1E4E8;--shiki-sepia:#F8F8F2"},"children":[{"type":"text","value":"."}]},{"type":"element","tag":"span","props":{"style":"--shiki-light:#90A4AE;--shiki-default:#005CC5;--shiki-dark:#79B8FF;--shiki-sepia:#F8F8F2"},"children":[{"type":"text","value":"prototype"}]},{"type":"element","tag":"span","props":{"style":"--shiki-light:#39ADB5;--shiki-default:#24292E;--shiki-dark:#E1E4E8;--shiki-sepia:#F8F8F2"},"children":[{"type":"text","value":"."}]},{"type":"element","tag":"span","props":{"style":"--shiki-light:#90A4AE;--shiki-default:#24292E;--shiki-dark:#E1E4E8;--shiki-sepia:#F8F8F2"},"children":[{"type":"text","value":"slice"}]},{"type":"element","tag":"span","props":{"style":"--shiki-light:#39ADB5;--shiki-default:#24292E;--shiki-dark:#E1E4E8;--shiki-sepia:#F8F8F2"},"children":[{"type":"text","value":"."}]},{"type":"element","tag":"span","props":{"style":"--shiki-light:#6182B8;--shiki-default:#6F42C1;--shiki-dark:#B392F0;--shiki-sepia:#A6E22E"},"children":[{"type":"text","value":"call"}]},{"type":"element","tag":"span","props":{"style":"--shiki-light:#90A4AE;--shiki-default:#24292E;--shiki-dark:#E1E4E8;--shiki-sepia:#F8F8F2"},"children":[{"type":"text","value":"(something)\n"}]}]}]}]},{"type":"element","tag":"p","props":{},"children":[{"type":"text","value":"不过框架外围，需要有一个补丁（概念），修补 Array.prototype.slice 函数。这样使得框架逻辑与浏览器兼容逻辑解耦，将来“框架升级时便能轻松抛弃这些历史包袱”。"}]},{"type":"element","tag":"p","props":{},"children":[{"type":"text","value":"这里重现一下思路："}]},{"type":"element","tag":"pre","props":{"className":"language-js shiki shiki-themes material-theme-lighter github-light github-dark monokai","code":"(function() {\n    const _slice = Array.prototype.slice\n    try {\n        _slice.call(document.documentElement)\n    } catch () {\n        Array.prototype.slice = function (i, j) {\n            i = i || 0\n            j = j || this.length\n            if (Object.prototype.toString.call(this) === '[object Array]') {\n                return _slice.call(this, i, j)\n            }\n            const start = i > 0 ? i : i + this.length\n            const end = j > 0 ? j : j + this.length\n            let size = end - start, cloned\n            if (size > 0) {\n                cloned = new Array(size)\n                let p = 0\n                while (p++ < size) {\n                    if (this.charAt) {\n                        cloned[p] = this.charAt(p)\n                    } else {\n                        cloned[p] = this[p]\n                    }\n                }\n            }\n            return cloned\n        }\n    }\n}())\n","language":"js","meta":"","style":""},"children":[{"type":"element","tag":"code","props":{"__ignoreMap":""},"children":[{"type":"element","tag":"span","props":{"class":"line","line":1},"children":[{"type":"element","tag":"span","props":{"style":"--shiki-light:#90A4AE;--shiki-default:#24292E;--shiki-dark:#E1E4E8;--shiki-sepia:#F8F8F2"},"children":[{"type":"text","value":"("}]},{"type":"element","tag":"span","props":{"style":"--shiki-light:#9C3EDA;--shiki-default:#D73A49;--shiki-dark:#F97583;--shiki-sepia:#66D9EF;--shiki-light-font-style:inherit;--shiki-default-font-style:inherit;--shiki-dark-font-style:inherit;--shiki-sepia-font-style:italic"},"children":[{"type":"text","value":"function"}]},{"type":"element","tag":"span","props":{"style":"--shiki-light:#39ADB5;--shiki-default:#24292E;--shiki-dark:#E1E4E8;--shiki-sepia:#F8F8F2"},"children":[{"type":"text","value":"()"}]},{"type":"element","tag":"span","props":{"style":"--shiki-light:#39ADB5;--shiki-default:#24292E;--shiki-dark:#E1E4E8;--shiki-sepia:#F8F8F2"},"children":[{"type":"text","value":" {\n"}]}]},{"type":"element","tag":"span","props":{"class":"line","line":2},"children":[{"type":"element","tag":"span","props":{"style":"--shiki-light:#9C3EDA;--shiki-default:#D73A49;--shiki-dark:#F97583;--shiki-sepia:#66D9EF;--shiki-light-font-style:inherit;--shiki-default-font-style:inherit;--shiki-dark-font-style:inherit;--shiki-sepia-font-style:italic"},"children":[{"type":"text","value":"    const"}]},{"type":"element","tag":"span","props":{"style":"--shiki-light:#90A4AE;--shiki-default:#005CC5;--shiki-dark:#79B8FF;--shiki-sepia:#F8F8F2"},"children":[{"type":"text","value":" _slice"}]},{"type":"element","tag":"span","props":{"style":"--shiki-light:#39ADB5;--shiki-default:#D73A49;--shiki-dark:#F97583;--shiki-sepia:#F92672"},"children":[{"type":"text","value":" ="}]},{"type":"element","tag":"span","props":{"style":"--shiki-light:#E2931D;--shiki-default:#005CC5;--shiki-dark:#79B8FF;--shiki-sepia:#66D9EF;--shiki-light-font-style:inherit;--shiki-default-font-style:inherit;--shiki-dark-font-style:inherit;--shiki-sepia-font-style:italic"},"children":[{"type":"text","value":" Array"}]},{"type":"element","tag":"span","props":{"style":"--shiki-light:#39ADB5;--shiki-default:#24292E;--shiki-dark:#E1E4E8;--shiki-sepia:#F8F8F2"},"children":[{"type":"text","value":"."}]},{"type":"element","tag":"span","props":{"style":"--shiki-light:#90A4AE;--shiki-default:#005CC5;--shiki-dark:#79B8FF;--shiki-sepia:#F8F8F2"},"children":[{"type":"text","value":"prototype"}]},{"type":"element","tag":"span","props":{"style":"--shiki-light:#39ADB5;--shiki-default:#24292E;--shiki-dark:#E1E4E8;--shiki-sepia:#F8F8F2"},"children":[{"type":"text","value":"."}]},{"type":"element","tag":"span","props":{"style":"--shiki-light:#90A4AE;--shiki-default:#24292E;--shiki-dark:#E1E4E8;--shiki-sepia:#F8F8F2"},"children":[{"type":"text","value":"slice\n"}]}]},{"type":"element","tag":"span","props":{"class":"line","line":3},"children":[{"type":"element","tag":"span","props":{"style":"--shiki-light:#39ADB5;--shiki-default:#D73A49;--shiki-dark:#F97583;--shiki-sepia:#F92672;--shiki-light-font-style:italic;--shiki-default-font-style:inherit;--shiki-dark-font-style:inherit;--shiki-sepia-font-style:inherit"},"children":[{"type":"text","value":"    try"}]},{"type":"element","tag":"span","props":{"style":"--shiki-light:#39ADB5;--shiki-default:#24292E;--shiki-dark:#E1E4E8;--shiki-sepia:#F8F8F2"},"children":[{"type":"text","value":" {\n"}]}]},{"type":"element","tag":"span","props":{"class":"line","line":4},"children":[{"type":"element","tag":"span","props":{"style":"--shiki-light:#90A4AE;--shiki-default:#24292E;--shiki-dark:#E1E4E8;--shiki-sepia:#F8F8F2"},"children":[{"type":"text","value":"        _slice"}]},{"type":"element","tag":"span","props":{"style":"--shiki-light:#39ADB5;--shiki-default:#24292E;--shiki-dark:#E1E4E8;--shiki-sepia:#F8F8F2"},"children":[{"type":"text","value":"."}]},{"type":"element","tag":"span","props":{"style":"--shiki-light:#6182B8;--shiki-default:#6F42C1;--shiki-dark:#B392F0;--shiki-sepia:#A6E22E"},"children":[{"type":"text","value":"call"}]},{"type":"element","tag":"span","props":{"style":"--shiki-light:#E53935;--shiki-default:#24292E;--shiki-dark:#E1E4E8;--shiki-sepia:#F8F8F2"},"children":[{"type":"text","value":"("}]},{"type":"element","tag":"span","props":{"style":"--shiki-light:#90A4AE;--shiki-default:#24292E;--shiki-dark:#E1E4E8;--shiki-sepia:#F8F8F2"},"children":[{"type":"text","value":"document"}]},{"type":"element","tag":"span","props":{"style":"--shiki-light:#39ADB5;--shiki-default:#24292E;--shiki-dark:#E1E4E8;--shiki-sepia:#F8F8F2"},"children":[{"type":"text","value":"."}]},{"type":"element","tag":"span","props":{"style":"--shiki-light:#90A4AE;--shiki-default:#24292E;--shiki-dark:#E1E4E8;--shiki-sepia:#F8F8F2"},"children":[{"type":"text","value":"documentElement"}]},{"type":"element","tag":"span","props":{"style":"--shiki-light:#E53935;--shiki-default:#24292E;--shiki-dark:#E1E4E8;--shiki-sepia:#F8F8F2"},"children":[{"type":"text","value":")\n"}]}]},{"type":"element","tag":"span","props":{"class":"line","line":5},"children":[{"type":"element","tag":"span","props":{"style":"--shiki-light:#39ADB5;--shiki-default:#24292E;--shiki-dark:#E1E4E8;--shiki-sepia:#F8F8F2"},"children":[{"type":"text","value":"    }"}]},{"type":"element","tag":"span","props":{"style":"--shiki-light:#39ADB5;--shiki-default:#D73A49;--shiki-dark:#F97583;--shiki-sepia:#F92672;--shiki-light-font-style:italic;--shiki-default-font-style:inherit;--shiki-dark-font-style:inherit;--shiki-sepia-font-style:inherit"},"children":[{"type":"text","value":" catch"}]},{"type":"element","tag":"span","props":{"style":"--shiki-light:#E53935;--shiki-default:#24292E;--shiki-dark:#E1E4E8;--shiki-sepia:#F8F8F2"},"children":[{"type":"text","value":" () "}]},{"type":"element","tag":"span","props":{"style":"--shiki-light:#39ADB5;--shiki-default:#24292E;--shiki-dark:#E1E4E8;--shiki-sepia:#F8F8F2"},"children":[{"type":"text","value":"{\n"}]}]},{"type":"element","tag":"span","props":{"class":"line","line":6},"children":[{"type":"element","tag":"span","props":{"style":"--shiki-light:#E2931D;--shiki-default:#005CC5;--shiki-dark:#79B8FF;--shiki-sepia:#66D9EF;--shiki-light-font-style:inherit;--shiki-default-font-style:inherit;--shiki-dark-font-style:inherit;--shiki-sepia-font-style:italic"},"children":[{"type":"text","value":"        Array"}]},{"type":"element","tag":"span","props":{"style":"--shiki-light:#39ADB5;--shiki-default:#24292E;--shiki-dark:#E1E4E8;--shiki-sepia:#F8F8F2"},"children":[{"type":"text","value":"."}]},{"type":"element","tag":"span","props":{"style":"--shiki-light:#90A4AE;--shiki-default:#005CC5;--shiki-dark:#79B8FF;--shiki-sepia:#F8F8F2"},"children":[{"type":"text","value":"prototype"}]},{"type":"element","tag":"span","props":{"style":"--shiki-light:#39ADB5;--shiki-default:#24292E;--shiki-dark:#E1E4E8;--shiki-sepia:#F8F8F2"},"children":[{"type":"text","value":"."}]},{"type":"element","tag":"span","props":{"style":"--shiki-light:#6182B8;--shiki-default:#6F42C1;--shiki-dark:#B392F0;--shiki-sepia:#A6E22E"},"children":[{"type":"text","value":"slice"}]},{"type":"element","tag":"span","props":{"style":"--shiki-light:#39ADB5;--shiki-default:#D73A49;--shiki-dark:#F97583;--shiki-sepia:#F92672"},"children":[{"type":"text","value":" ="}]},{"type":"element","tag":"span","props":{"style":"--shiki-light:#9C3EDA;--shiki-default:#D73A49;--shiki-dark:#F97583;--shiki-sepia:#66D9EF;--shiki-light-font-style:inherit;--shiki-default-font-style:inherit;--shiki-dark-font-style:inherit;--shiki-sepia-font-style:italic"},"children":[{"type":"text","value":" function"}]},{"type":"element","tag":"span","props":{"style":"--shiki-light:#39ADB5;--shiki-default:#24292E;--shiki-dark:#E1E4E8;--shiki-sepia:#F8F8F2"},"children":[{"type":"text","value":" ("}]},{"type":"element","tag":"span","props":{"style":"--shiki-light:#90A4AE;--shiki-default:#E36209;--shiki-dark:#FFAB70;--shiki-sepia:#FD971F;--shiki-light-font-style:italic;--shiki-default-font-style:inherit;--shiki-dark-font-style:inherit;--shiki-sepia-font-style:italic"},"children":[{"type":"text","value":"i"}]},{"type":"element","tag":"span","props":{"style":"--shiki-light:#39ADB5;--shiki-default:#24292E;--shiki-dark:#E1E4E8;--shiki-sepia:#F8F8F2"},"children":[{"type":"text","value":","}]},{"type":"element","tag":"span","props":{"style":"--shiki-light:#90A4AE;--shiki-default:#E36209;--shiki-dark:#FFAB70;--shiki-sepia:#FD971F;--shiki-light-font-style:italic;--shiki-default-font-style:inherit;--shiki-dark-font-style:inherit;--shiki-sepia-font-style:italic"},"children":[{"type":"text","value":" j"}]},{"type":"element","tag":"span","props":{"style":"--shiki-light:#39ADB5;--shiki-default:#24292E;--shiki-dark:#E1E4E8;--shiki-sepia:#F8F8F2"},"children":[{"type":"text","value":")"}]},{"type":"element","tag":"span","props":{"style":"--shiki-light:#39ADB5;--shiki-default:#24292E;--shiki-dark:#E1E4E8;--shiki-sepia:#F8F8F2"},"children":[{"type":"text","value":" {\n"}]}]},{"type":"element","tag":"span","props":{"class":"line","line":7},"children":[{"type":"element","tag":"span","props":{"style":"--shiki-light:#90A4AE;--shiki-default:#24292E;--shiki-dark:#E1E4E8;--shiki-sepia:#F8F8F2"},"children":[{"type":"text","value":"            i"}]},{"type":"element","tag":"span","props":{"style":"--shiki-light:#39ADB5;--shiki-default:#D73A49;--shiki-dark:#F97583;--shiki-sepia:#F92672"},"children":[{"type":"text","value":" ="}]},{"type":"element","tag":"span","props":{"style":"--shiki-light:#90A4AE;--shiki-default:#24292E;--shiki-dark:#E1E4E8;--shiki-sepia:#F8F8F2"},"children":[{"type":"text","value":" i"}]},{"type":"element","tag":"span","props":{"style":"--shiki-light:#39ADB5;--shiki-default:#D73A49;--shiki-dark:#F97583;--shiki-sepia:#F92672"},"children":[{"type":"text","value":" ||"}]},{"type":"element","tag":"span","props":{"style":"--shiki-light:#F76D47;--shiki-default:#005CC5;--shiki-dark:#79B8FF;--shiki-sepia:#AE81FF"},"children":[{"type":"text","value":" 0\n"}]}]},{"type":"element","tag":"span","props":{"class":"line","line":8},"children":[{"type":"element","tag":"span","props":{"style":"--shiki-light:#90A4AE;--shiki-default:#24292E;--shiki-dark:#E1E4E8;--shiki-sepia:#F8F8F2"},"children":[{"type":"text","value":"            j"}]},{"type":"element","tag":"span","props":{"style":"--shiki-light:#39ADB5;--shiki-default:#D73A49;--shiki-dark:#F97583;--shiki-sepia:#F92672"},"children":[{"type":"text","value":" ="}]},{"type":"element","tag":"span","props":{"style":"--shiki-light:#90A4AE;--shiki-default:#24292E;--shiki-dark:#E1E4E8;--shiki-sepia:#F8F8F2"},"children":[{"type":"text","value":" j"}]},{"type":"element","tag":"span","props":{"style":"--shiki-light:#39ADB5;--shiki-default:#D73A49;--shiki-dark:#F97583;--shiki-sepia:#F92672"},"children":[{"type":"text","value":" ||"}]},{"type":"element","tag":"span","props":{"style":"--shiki-light:#39ADB5;--shiki-default:#005CC5;--shiki-dark:#79B8FF;--shiki-sepia:#FD971F"},"children":[{"type":"text","value":" this"}]},{"type":"element","tag":"span","props":{"style":"--shiki-light:#39ADB5;--shiki-default:#24292E;--shiki-dark:#E1E4E8;--shiki-sepia:#F8F8F2"},"children":[{"type":"text","value":"."}]},{"type":"element","tag":"span","props":{"style":"--shiki-light:#90A4AE;--shiki-default:#005CC5;--shiki-dark:#79B8FF;--shiki-sepia:#F8F8F2"},"children":[{"type":"text","value":"length\n"}]}]},{"type":"element","tag":"span","props":{"class":"line","line":9},"children":[{"type":"element","tag":"span","props":{"style":"--shiki-light:#39ADB5;--shiki-default:#D73A49;--shiki-dark:#F97583;--shiki-sepia:#F92672;--shiki-light-font-style:italic;--shiki-default-font-style:inherit;--shiki-dark-font-style:inherit;--shiki-sepia-font-style:inherit"},"children":[{"type":"text","value":"            if"}]},{"type":"element","tag":"span","props":{"style":"--shiki-light:#E53935;--shiki-default:#24292E;--shiki-dark:#E1E4E8;--shiki-sepia:#F8F8F2"},"children":[{"type":"text","value":" ("}]},{"type":"element","tag":"span","props":{"style":"--shiki-light:#E2931D;--shiki-default:#005CC5;--shiki-dark:#79B8FF;--shiki-sepia:#66D9EF;--shiki-light-font-style:inherit;--shiki-default-font-style:inherit;--shiki-dark-font-style:inherit;--shiki-sepia-font-style:italic"},"children":[{"type":"text","value":"Object"}]},{"type":"element","tag":"span","props":{"style":"--shiki-light:#39ADB5;--shiki-default:#24292E;--shiki-dark:#E1E4E8;--shiki-sepia:#F8F8F2"},"children":[{"type":"text","value":"."}]},{"type":"element","tag":"span","props":{"style":"--shiki-light:#90A4AE;--shiki-default:#005CC5;--shiki-dark:#79B8FF;--shiki-sepia:#F8F8F2"},"children":[{"type":"text","value":"prototype"}]},{"type":"element","tag":"span","props":{"style":"--shiki-light:#39ADB5;--shiki-default:#24292E;--shiki-dark:#E1E4E8;--shiki-sepia:#F8F8F2"},"children":[{"type":"text","value":"."}]},{"type":"element","tag":"span","props":{"style":"--shiki-light:#90A4AE;--shiki-default:#24292E;--shiki-dark:#E1E4E8;--shiki-sepia:#F8F8F2"},"children":[{"type":"text","value":"toString"}]},{"type":"element","tag":"span","props":{"style":"--shiki-light:#39ADB5;--shiki-default:#24292E;--shiki-dark:#E1E4E8;--shiki-sepia:#F8F8F2"},"children":[{"type":"text","value":"."}]},{"type":"element","tag":"span","props":{"style":"--shiki-light:#6182B8;--shiki-default:#6F42C1;--shiki-dark:#B392F0;--shiki-sepia:#A6E22E"},"children":[{"type":"text","value":"call"}]},{"type":"element","tag":"span","props":{"style":"--shiki-light:#E53935;--shiki-default:#24292E;--shiki-dark:#E1E4E8;--shiki-sepia:#F8F8F2"},"children":[{"type":"text","value":"("}]},{"type":"element","tag":"span","props":{"style":"--shiki-light:#39ADB5;--shiki-default:#005CC5;--shiki-dark:#79B8FF;--shiki-sepia:#FD971F"},"children":[{"type":"text","value":"this"}]},{"type":"element","tag":"span","props":{"style":"--shiki-light:#E53935;--shiki-default:#24292E;--shiki-dark:#E1E4E8;--shiki-sepia:#F8F8F2"},"children":[{"type":"text","value":") "}]},{"type":"element","tag":"span","props":{"style":"--shiki-light:#39ADB5;--shiki-default:#D73A49;--shiki-dark:#F97583;--shiki-sepia:#F92672"},"children":[{"type":"text","value":"==="}]},{"type":"element","tag":"span","props":{"style":"--shiki-light:#39ADB5;--shiki-default:#032F62;--shiki-dark:#9ECBFF;--shiki-sepia:#E6DB74"},"children":[{"type":"text","value":" '"}]},{"type":"element","tag":"span","props":{"style":"--shiki-light:#91B859;--shiki-default:#032F62;--shiki-dark:#9ECBFF;--shiki-sepia:#E6DB74"},"children":[{"type":"text","value":"[object Array]"}]},{"type":"element","tag":"span","props":{"style":"--shiki-light:#39ADB5;--shiki-default:#032F62;--shiki-dark:#9ECBFF;--shiki-sepia:#E6DB74"},"children":[{"type":"text","value":"'"}]},{"type":"element","tag":"span","props":{"style":"--shiki-light:#E53935;--shiki-default:#24292E;--shiki-dark:#E1E4E8;--shiki-sepia:#F8F8F2"},"children":[{"type":"text","value":") "}]},{"type":"element","tag":"span","props":{"style":"--shiki-light:#39ADB5;--shiki-default:#24292E;--shiki-dark:#E1E4E8;--shiki-sepia:#F8F8F2"},"children":[{"type":"text","value":"{\n"}]}]},{"type":"element","tag":"span","props":{"class":"line","line":10},"children":[{"type":"element","tag":"span","props":{"style":"--shiki-light:#39ADB5;--shiki-default:#D73A49;--shiki-dark:#F97583;--shiki-sepia:#F92672;--shiki-light-font-style:italic;--shiki-default-font-style:inherit;--shiki-dark-font-style:inherit;--shiki-sepia-font-style:inherit"},"children":[{"type":"text","value":"                return"}]},{"type":"element","tag":"span","props":{"style":"--shiki-light:#90A4AE;--shiki-default:#24292E;--shiki-dark:#E1E4E8;--shiki-sepia:#F8F8F2"},"children":[{"type":"text","value":" _slice"}]},{"type":"element","tag":"span","props":{"style":"--shiki-light:#39ADB5;--shiki-default:#24292E;--shiki-dark:#E1E4E8;--shiki-sepia:#F8F8F2"},"children":[{"type":"text","value":"."}]},{"type":"element","tag":"span","props":{"style":"--shiki-light:#6182B8;--shiki-default:#6F42C1;--shiki-dark:#B392F0;--shiki-sepia:#A6E22E"},"children":[{"type":"text","value":"call"}]},{"type":"element","tag":"span","props":{"style":"--shiki-light:#E53935;--shiki-default:#24292E;--shiki-dark:#E1E4E8;--shiki-sepia:#F8F8F2"},"children":[{"type":"text","value":"("}]},{"type":"element","tag":"span","props":{"style":"--shiki-light:#39ADB5;--shiki-default:#005CC5;--shiki-dark:#79B8FF;--shiki-sepia:#FD971F"},"children":[{"type":"text","value":"this"}]},{"type":"element","tag":"span","props":{"style":"--shiki-light:#39ADB5;--shiki-default:#24292E;--shiki-dark:#E1E4E8;--shiki-sepia:#F8F8F2"},"children":[{"type":"text","value":","}]},{"type":"element","tag":"span","props":{"style":"--shiki-light:#90A4AE;--shiki-default:#24292E;--shiki-dark:#E1E4E8;--shiki-sepia:#F8F8F2"},"children":[{"type":"text","value":" i"}]},{"type":"element","tag":"span","props":{"style":"--shiki-light:#39ADB5;--shiki-default:#24292E;--shiki-dark:#E1E4E8;--shiki-sepia:#F8F8F2"},"children":[{"type":"text","value":","}]},{"type":"element","tag":"span","props":{"style":"--shiki-light:#90A4AE;--shiki-default:#24292E;--shiki-dark:#E1E4E8;--shiki-sepia:#F8F8F2"},"children":[{"type":"text","value":" j"}]},{"type":"element","tag":"span","props":{"style":"--shiki-light:#E53935;--shiki-default:#24292E;--shiki-dark:#E1E4E8;--shiki-sepia:#F8F8F2"},"children":[{"type":"text","value":")\n"}]}]},{"type":"element","tag":"span","props":{"class":"line","line":11},"children":[{"type":"element","tag":"span","props":{"style":"--shiki-light:#39ADB5;--shiki-default:#24292E;--shiki-dark:#E1E4E8;--shiki-sepia:#F8F8F2"},"children":[{"type":"text","value":"            }\n"}]}]},{"type":"element","tag":"span","props":{"class":"line","line":12},"children":[{"type":"element","tag":"span","props":{"style":"--shiki-light:#9C3EDA;--shiki-default:#D73A49;--shiki-dark:#F97583;--shiki-sepia:#66D9EF;--shiki-light-font-style:inherit;--shiki-default-font-style:inherit;--shiki-dark-font-style:inherit;--shiki-sepia-font-style:italic"},"children":[{"type":"text","value":"            const"}]},{"type":"element","tag":"span","props":{"style":"--shiki-light:#90A4AE;--shiki-default:#005CC5;--shiki-dark:#79B8FF;--shiki-sepia:#F8F8F2"},"children":[{"type":"text","value":" start"}]},{"type":"element","tag":"span","props":{"style":"--shiki-light:#39ADB5;--shiki-default:#D73A49;--shiki-dark:#F97583;--shiki-sepia:#F92672"},"children":[{"type":"text","value":" ="}]},{"type":"element","tag":"span","props":{"style":"--shiki-light:#90A4AE;--shiki-default:#24292E;--shiki-dark:#E1E4E8;--shiki-sepia:#F8F8F2"},"children":[{"type":"text","value":" i"}]},{"type":"element","tag":"span","props":{"style":"--shiki-light:#39ADB5;--shiki-default:#D73A49;--shiki-dark:#F97583;--shiki-sepia:#F92672"},"children":[{"type":"text","value":" >"}]},{"type":"element","tag":"span","props":{"style":"--shiki-light:#F76D47;--shiki-default:#005CC5;--shiki-dark:#79B8FF;--shiki-sepia:#AE81FF"},"children":[{"type":"text","value":" 0"}]},{"type":"element","tag":"span","props":{"style":"--shiki-light:#39ADB5;--shiki-default:#D73A49;--shiki-dark:#F97583;--shiki-sepia:#F92672"},"children":[{"type":"text","value":" ?"}]},{"type":"element","tag":"span","props":{"style":"--shiki-light:#90A4AE;--shiki-default:#24292E;--shiki-dark:#E1E4E8;--shiki-sepia:#F8F8F2"},"children":[{"type":"text","value":" i"}]},{"type":"element","tag":"span","props":{"style":"--shiki-light:#39ADB5;--shiki-default:#D73A49;--shiki-dark:#F97583;--shiki-sepia:#F92672"},"children":[{"type":"text","value":" :"}]},{"type":"element","tag":"span","props":{"style":"--shiki-light:#90A4AE;--shiki-default:#24292E;--shiki-dark:#E1E4E8;--shiki-sepia:#F8F8F2"},"children":[{"type":"text","value":" i"}]},{"type":"element","tag":"span","props":{"style":"--shiki-light:#39ADB5;--shiki-default:#D73A49;--shiki-dark:#F97583;--shiki-sepia:#F92672"},"children":[{"type":"text","value":" +"}]},{"type":"element","tag":"span","props":{"style":"--shiki-light:#39ADB5;--shiki-default:#005CC5;--shiki-dark:#79B8FF;--shiki-sepia:#FD971F"},"children":[{"type":"text","value":" this"}]},{"type":"element","tag":"span","props":{"style":"--shiki-light:#39ADB5;--shiki-default:#24292E;--shiki-dark:#E1E4E8;--shiki-sepia:#F8F8F2"},"children":[{"type":"text","value":"."}]},{"type":"element","tag":"span","props":{"style":"--shiki-light:#90A4AE;--shiki-default:#005CC5;--shiki-dark:#79B8FF;--shiki-sepia:#F8F8F2"},"children":[{"type":"text","value":"length\n"}]}]},{"type":"element","tag":"span","props":{"class":"line","line":13},"children":[{"type":"element","tag":"span","props":{"style":"--shiki-light:#9C3EDA;--shiki-default:#D73A49;--shiki-dark:#F97583;--shiki-sepia:#66D9EF;--shiki-light-font-style:inherit;--shiki-default-font-style:inherit;--shiki-dark-font-style:inherit;--shiki-sepia-font-style:italic"},"children":[{"type":"text","value":"            const"}]},{"type":"element","tag":"span","props":{"style":"--shiki-light:#90A4AE;--shiki-default:#005CC5;--shiki-dark:#79B8FF;--shiki-sepia:#F8F8F2"},"children":[{"type":"text","value":" end"}]},{"type":"element","tag":"span","props":{"style":"--shiki-light:#39ADB5;--shiki-default:#D73A49;--shiki-dark:#F97583;--shiki-sepia:#F92672"},"children":[{"type":"text","value":" ="}]},{"type":"element","tag":"span","props":{"style":"--shiki-light:#90A4AE;--shiki-default:#24292E;--shiki-dark:#E1E4E8;--shiki-sepia:#F8F8F2"},"children":[{"type":"text","value":" j"}]},{"type":"element","tag":"span","props":{"style":"--shiki-light:#39ADB5;--shiki-default:#D73A49;--shiki-dark:#F97583;--shiki-sepia:#F92672"},"children":[{"type":"text","value":" >"}]},{"type":"element","tag":"span","props":{"style":"--shiki-light:#F76D47;--shiki-default:#005CC5;--shiki-dark:#79B8FF;--shiki-sepia:#AE81FF"},"children":[{"type":"text","value":" 0"}]},{"type":"element","tag":"span","props":{"style":"--shiki-light:#39ADB5;--shiki-default:#D73A49;--shiki-dark:#F97583;--shiki-sepia:#F92672"},"children":[{"type":"text","value":" ?"}]},{"type":"element","tag":"span","props":{"style":"--shiki-light:#90A4AE;--shiki-default:#24292E;--shiki-dark:#E1E4E8;--shiki-sepia:#F8F8F2"},"children":[{"type":"text","value":" j"}]},{"type":"element","tag":"span","props":{"style":"--shiki-light:#39ADB5;--shiki-default:#D73A49;--shiki-dark:#F97583;--shiki-sepia:#F92672"},"children":[{"type":"text","value":" :"}]},{"type":"element","tag":"span","props":{"style":"--shiki-light:#90A4AE;--shiki-default:#24292E;--shiki-dark:#E1E4E8;--shiki-sepia:#F8F8F2"},"children":[{"type":"text","value":" j"}]},{"type":"element","tag":"span","props":{"style":"--shiki-light:#39ADB5;--shiki-default:#D73A49;--shiki-dark:#F97583;--shiki-sepia:#F92672"},"children":[{"type":"text","value":" +"}]},{"type":"element","tag":"span","props":{"style":"--shiki-light:#39ADB5;--shiki-default:#005CC5;--shiki-dark:#79B8FF;--shiki-sepia:#FD971F"},"children":[{"type":"text","value":" this"}]},{"type":"element","tag":"span","props":{"style":"--shiki-light:#39ADB5;--shiki-default:#24292E;--shiki-dark:#E1E4E8;--shiki-sepia:#F8F8F2"},"children":[{"type":"text","value":"."}]},{"type":"element","tag":"span","props":{"style":"--shiki-light:#90A4AE;--shiki-default:#005CC5;--shiki-dark:#79B8FF;--shiki-sepia:#F8F8F2"},"children":[{"type":"text","value":"length\n"}]}]},{"type":"element","tag":"span","props":{"class":"line","line":14},"children":[{"type":"element","tag":"span","props":{"style":"--shiki-light:#9C3EDA;--shiki-default:#D73A49;--shiki-dark:#F97583;--shiki-sepia:#66D9EF;--shiki-light-font-style:inherit;--shiki-default-font-style:inherit;--shiki-dark-font-style:inherit;--shiki-sepia-font-style:italic"},"children":[{"type":"text","value":"            let"}]},{"type":"element","tag":"span","props":{"style":"--shiki-light:#90A4AE;--shiki-default:#24292E;--shiki-dark:#E1E4E8;--shiki-sepia:#F8F8F2"},"children":[{"type":"text","value":" size"}]},{"type":"element","tag":"span","props":{"style":"--shiki-light:#39ADB5;--shiki-default:#D73A49;--shiki-dark:#F97583;--shiki-sepia:#F92672"},"children":[{"type":"text","value":" ="}]},{"type":"element","tag":"span","props":{"style":"--shiki-light:#90A4AE;--shiki-default:#24292E;--shiki-dark:#E1E4E8;--shiki-sepia:#F8F8F2"},"children":[{"type":"text","value":" end"}]},{"type":"element","tag":"span","props":{"style":"--shiki-light:#39ADB5;--shiki-default:#D73A49;--shiki-dark:#F97583;--shiki-sepia:#F92672"},"children":[{"type":"text","value":" -"}]},{"type":"element","tag":"span","props":{"style":"--shiki-light:#90A4AE;--shiki-default:#24292E;--shiki-dark:#E1E4E8;--shiki-sepia:#F8F8F2"},"children":[{"type":"text","value":" start"}]},{"type":"element","tag":"span","props":{"style":"--shiki-light:#39ADB5;--shiki-default:#24292E;--shiki-dark:#E1E4E8;--shiki-sepia:#F8F8F2"},"children":[{"type":"text","value":","}]},{"type":"element","tag":"span","props":{"style":"--shiki-light:#90A4AE;--shiki-default:#24292E;--shiki-dark:#E1E4E8;--shiki-sepia:#F8F8F2"},"children":[{"type":"text","value":" cloned\n"}]}]},{"type":"element","tag":"span","props":{"class":"line","line":15},"children":[{"type":"element","tag":"span","props":{"style":"--shiki-light:#39ADB5;--shiki-default:#D73A49;--shiki-dark:#F97583;--shiki-sepia:#F92672;--shiki-light-font-style:italic;--shiki-default-font-style:inherit;--shiki-dark-font-style:inherit;--shiki-sepia-font-style:inherit"},"children":[{"type":"text","value":"            if"}]},{"type":"element","tag":"span","props":{"style":"--shiki-light:#E53935;--shiki-default:#24292E;--shiki-dark:#E1E4E8;--shiki-sepia:#F8F8F2"},"children":[{"type":"text","value":" ("}]},{"type":"element","tag":"span","props":{"style":"--shiki-light:#90A4AE;--shiki-default:#24292E;--shiki-dark:#E1E4E8;--shiki-sepia:#F8F8F2"},"children":[{"type":"text","value":"size"}]},{"type":"element","tag":"span","props":{"style":"--shiki-light:#39ADB5;--shiki-default:#D73A49;--shiki-dark:#F97583;--shiki-sepia:#F92672"},"children":[{"type":"text","value":" >"}]},{"type":"element","tag":"span","props":{"style":"--shiki-light:#F76D47;--shiki-default:#005CC5;--shiki-dark:#79B8FF;--shiki-sepia:#AE81FF"},"children":[{"type":"text","value":" 0"}]},{"type":"element","tag":"span","props":{"style":"--shiki-light:#E53935;--shiki-default:#24292E;--shiki-dark:#E1E4E8;--shiki-sepia:#F8F8F2"},"children":[{"type":"text","value":") "}]},{"type":"element","tag":"span","props":{"style":"--shiki-light:#39ADB5;--shiki-default:#24292E;--shiki-dark:#E1E4E8;--shiki-sepia:#F8F8F2"},"children":[{"type":"text","value":"{\n"}]}]},{"type":"element","tag":"span","props":{"class":"line","line":16},"children":[{"type":"element","tag":"span","props":{"style":"--shiki-light:#90A4AE;--shiki-default:#24292E;--shiki-dark:#E1E4E8;--shiki-sepia:#F8F8F2"},"children":[{"type":"text","value":"                cloned"}]},{"type":"element","tag":"span","props":{"style":"--shiki-light:#39ADB5;--shiki-default:#D73A49;--shiki-dark:#F97583;--shiki-sepia:#F92672"},"children":[{"type":"text","value":" ="}]},{"type":"element","tag":"span","props":{"style":"--shiki-light:#39ADB5;--shiki-default:#D73A49;--shiki-dark:#F97583;--shiki-sepia:#F92672"},"children":[{"type":"text","value":" new"}]},{"type":"element","tag":"span","props":{"style":"--shiki-light:#6182B8;--shiki-default:#6F42C1;--shiki-dark:#B392F0;--shiki-sepia:#A6E22E"},"children":[{"type":"text","value":" Array"}]},{"type":"element","tag":"span","props":{"style":"--shiki-light:#E53935;--shiki-default:#24292E;--shiki-dark:#E1E4E8;--shiki-sepia:#F8F8F2"},"children":[{"type":"text","value":"("}]},{"type":"element","tag":"span","props":{"style":"--shiki-light:#90A4AE;--shiki-default:#24292E;--shiki-dark:#E1E4E8;--shiki-sepia:#F8F8F2"},"children":[{"type":"text","value":"size"}]},{"type":"element","tag":"span","props":{"style":"--shiki-light:#E53935;--shiki-default:#24292E;--shiki-dark:#E1E4E8;--shiki-sepia:#F8F8F2"},"children":[{"type":"text","value":")\n"}]}]},{"type":"element","tag":"span","props":{"class":"line","line":17},"children":[{"type":"element","tag":"span","props":{"style":"--shiki-light:#9C3EDA;--shiki-default:#D73A49;--shiki-dark:#F97583;--shiki-sepia:#66D9EF;--shiki-light-font-style:inherit;--shiki-default-font-style:inherit;--shiki-dark-font-style:inherit;--shiki-sepia-font-style:italic"},"children":[{"type":"text","value":"                let"}]},{"type":"element","tag":"span","props":{"style":"--shiki-light:#90A4AE;--shiki-default:#24292E;--shiki-dark:#E1E4E8;--shiki-sepia:#F8F8F2"},"children":[{"type":"text","value":" p"}]},{"type":"element","tag":"span","props":{"style":"--shiki-light:#39ADB5;--shiki-default:#D73A49;--shiki-dark:#F97583;--shiki-sepia:#F92672"},"children":[{"type":"text","value":" ="}]},{"type":"element","tag":"span","props":{"style":"--shiki-light:#F76D47;--shiki-default:#005CC5;--shiki-dark:#79B8FF;--shiki-sepia:#AE81FF"},"children":[{"type":"text","value":" 0\n"}]}]},{"type":"element","tag":"span","props":{"class":"line","line":18},"children":[{"type":"element","tag":"span","props":{"style":"--shiki-light:#39ADB5;--shiki-default:#D73A49;--shiki-dark:#F97583;--shiki-sepia:#F92672;--shiki-light-font-style:italic;--shiki-default-font-style:inherit;--shiki-dark-font-style:inherit;--shiki-sepia-font-style:inherit"},"children":[{"type":"text","value":"                while"}]},{"type":"element","tag":"span","props":{"style":"--shiki-light:#E53935;--shiki-default:#24292E;--shiki-dark:#E1E4E8;--shiki-sepia:#F8F8F2"},"children":[{"type":"text","value":" ("}]},{"type":"element","tag":"span","props":{"style":"--shiki-light:#90A4AE;--shiki-default:#24292E;--shiki-dark:#E1E4E8;--shiki-sepia:#F8F8F2"},"children":[{"type":"text","value":"p"}]},{"type":"element","tag":"span","props":{"style":"--shiki-light:#39ADB5;--shiki-default:#D73A49;--shiki-dark:#F97583;--shiki-sepia:#F92672"},"children":[{"type":"text","value":"++"}]},{"type":"element","tag":"span","props":{"style":"--shiki-light:#39ADB5;--shiki-default:#D73A49;--shiki-dark:#F97583;--shiki-sepia:#F92672"},"children":[{"type":"text","value":" <"}]},{"type":"element","tag":"span","props":{"style":"--shiki-light:#90A4AE;--shiki-default:#24292E;--shiki-dark:#E1E4E8;--shiki-sepia:#F8F8F2"},"children":[{"type":"text","value":" size"}]},{"type":"element","tag":"span","props":{"style":"--shiki-light:#E53935;--shiki-default:#24292E;--shiki-dark:#E1E4E8;--shiki-sepia:#F8F8F2"},"children":[{"type":"text","value":") "}]},{"type":"element","tag":"span","props":{"style":"--shiki-light:#39ADB5;--shiki-default:#24292E;--shiki-dark:#E1E4E8;--shiki-sepia:#F8F8F2"},"children":[{"type":"text","value":"{\n"}]}]},{"type":"element","tag":"span","props":{"class":"line","line":19},"children":[{"type":"element","tag":"span","props":{"style":"--shiki-light:#39ADB5;--shiki-default:#D73A49;--shiki-dark:#F97583;--shiki-sepia:#F92672;--shiki-light-font-style:italic;--shiki-default-font-style:inherit;--shiki-dark-font-style:inherit;--shiki-sepia-font-style:inherit"},"children":[{"type":"text","value":"                    if"}]},{"type":"element","tag":"span","props":{"style":"--shiki-light:#E53935;--shiki-default:#24292E;--shiki-dark:#E1E4E8;--shiki-sepia:#F8F8F2"},"children":[{"type":"text","value":" ("}]},{"type":"element","tag":"span","props":{"style":"--shiki-light:#39ADB5;--shiki-default:#005CC5;--shiki-dark:#79B8FF;--shiki-sepia:#FD971F"},"children":[{"type":"text","value":"this"}]},{"type":"element","tag":"span","props":{"style":"--shiki-light:#39ADB5;--shiki-default:#24292E;--shiki-dark:#E1E4E8;--shiki-sepia:#F8F8F2"},"children":[{"type":"text","value":"."}]},{"type":"element","tag":"span","props":{"style":"--shiki-light:#90A4AE;--shiki-default:#24292E;--shiki-dark:#E1E4E8;--shiki-sepia:#F8F8F2"},"children":[{"type":"text","value":"charAt"}]},{"type":"element","tag":"span","props":{"style":"--shiki-light:#E53935;--shiki-default:#24292E;--shiki-dark:#E1E4E8;--shiki-sepia:#F8F8F2"},"children":[{"type":"text","value":") "}]},{"type":"element","tag":"span","props":{"style":"--shiki-light:#39ADB5;--shiki-default:#24292E;--shiki-dark:#E1E4E8;--shiki-sepia:#F8F8F2"},"children":[{"type":"text","value":"{\n"}]}]},{"type":"element","tag":"span","props":{"class":"line","line":20},"children":[{"type":"element","tag":"span","props":{"style":"--shiki-light:#90A4AE;--shiki-default:#24292E;--shiki-dark:#E1E4E8;--shiki-sepia:#F8F8F2"},"children":[{"type":"text","value":"                        cloned"}]},{"type":"element","tag":"span","props":{"style":"--shiki-light:#E53935;--shiki-default:#24292E;--shiki-dark:#E1E4E8;--shiki-sepia:#F8F8F2"},"children":[{"type":"text","value":"["}]},{"type":"element","tag":"span","props":{"style":"--shiki-light:#90A4AE;--shiki-default:#24292E;--shiki-dark:#E1E4E8;--shiki-sepia:#F8F8F2"},"children":[{"type":"text","value":"p"}]},{"type":"element","tag":"span","props":{"style":"--shiki-light:#E53935;--shiki-default:#24292E;--shiki-dark:#E1E4E8;--shiki-sepia:#F8F8F2"},"children":[{"type":"text","value":"] "}]},{"type":"element","tag":"span","props":{"style":"--shiki-light:#39ADB5;--shiki-default:#D73A49;--shiki-dark:#F97583;--shiki-sepia:#F92672"},"children":[{"type":"text","value":"="}]},{"type":"element","tag":"span","props":{"style":"--shiki-light:#39ADB5;--shiki-default:#005CC5;--shiki-dark:#79B8FF;--shiki-sepia:#FD971F"},"children":[{"type":"text","value":" this"}]},{"type":"element","tag":"span","props":{"style":"--shiki-light:#39ADB5;--shiki-default:#24292E;--shiki-dark:#E1E4E8;--shiki-sepia:#F8F8F2"},"children":[{"type":"text","value":"."}]},{"type":"element","tag":"span","props":{"style":"--shiki-light:#6182B8;--shiki-default:#6F42C1;--shiki-dark:#B392F0;--shiki-sepia:#A6E22E"},"children":[{"type":"text","value":"charAt"}]},{"type":"element","tag":"span","props":{"style":"--shiki-light:#E53935;--shiki-default:#24292E;--shiki-dark:#E1E4E8;--shiki-sepia:#F8F8F2"},"children":[{"type":"text","value":"("}]},{"type":"element","tag":"span","props":{"style":"--shiki-light:#90A4AE;--shiki-default:#24292E;--shiki-dark:#E1E4E8;--shiki-sepia:#F8F8F2"},"children":[{"type":"text","value":"p"}]},{"type":"element","tag":"span","props":{"style":"--shiki-light:#E53935;--shiki-default:#24292E;--shiki-dark:#E1E4E8;--shiki-sepia:#F8F8F2"},"children":[{"type":"text","value":")\n"}]}]},{"type":"element","tag":"span","props":{"class":"line","line":21},"children":[{"type":"element","tag":"span","props":{"style":"--shiki-light:#39ADB5;--shiki-default:#24292E;--shiki-dark:#E1E4E8;--shiki-sepia:#F8F8F2"},"children":[{"type":"text","value":"                    }"}]},{"type":"element","tag":"span","props":{"style":"--shiki-light:#39ADB5;--shiki-default:#D73A49;--shiki-dark:#F97583;--shiki-sepia:#F92672;--shiki-light-font-style:italic;--shiki-default-font-style:inherit;--shiki-dark-font-style:inherit;--shiki-sepia-font-style:inherit"},"children":[{"type":"text","value":" else"}]},{"type":"element","tag":"span","props":{"style":"--shiki-light:#39ADB5;--shiki-default:#24292E;--shiki-dark:#E1E4E8;--shiki-sepia:#F8F8F2"},"children":[{"type":"text","value":" {\n"}]}]},{"type":"element","tag":"span","props":{"class":"line","line":22},"children":[{"type":"element","tag":"span","props":{"style":"--shiki-light:#90A4AE;--shiki-default:#24292E;--shiki-dark:#E1E4E8;--shiki-sepia:#F8F8F2"},"children":[{"type":"text","value":"                        cloned"}]},{"type":"element","tag":"span","props":{"style":"--shiki-light:#E53935;--shiki-default:#24292E;--shiki-dark:#E1E4E8;--shiki-sepia:#F8F8F2"},"children":[{"type":"text","value":"["}]},{"type":"element","tag":"span","props":{"style":"--shiki-light:#90A4AE;--shiki-default:#24292E;--shiki-dark:#E1E4E8;--shiki-sepia:#F8F8F2"},"children":[{"type":"text","value":"p"}]},{"type":"element","tag":"span","props":{"style":"--shiki-light:#E53935;--shiki-default:#24292E;--shiki-dark:#E1E4E8;--shiki-sepia:#F8F8F2"},"children":[{"type":"text","value":"] "}]},{"type":"element","tag":"span","props":{"style":"--shiki-light:#39ADB5;--shiki-default:#D73A49;--shiki-dark:#F97583;--shiki-sepia:#F92672"},"children":[{"type":"text","value":"="}]},{"type":"element","tag":"span","props":{"style":"--shiki-light:#39ADB5;--shiki-default:#005CC5;--shiki-dark:#79B8FF;--shiki-sepia:#FD971F"},"children":[{"type":"text","value":" this"}]},{"type":"element","tag":"span","props":{"style":"--shiki-light:#E53935;--shiki-default:#24292E;--shiki-dark:#E1E4E8;--shiki-sepia:#F8F8F2"},"children":[{"type":"text","value":"["}]},{"type":"element","tag":"span","props":{"style":"--shiki-light:#90A4AE;--shiki-default:#24292E;--shiki-dark:#E1E4E8;--shiki-sepia:#F8F8F2"},"children":[{"type":"text","value":"p"}]},{"type":"element","tag":"span","props":{"style":"--shiki-light:#E53935;--shiki-default:#24292E;--shiki-dark:#E1E4E8;--shiki-sepia:#F8F8F2"},"children":[{"type":"text","value":"]\n"}]}]},{"type":"element","tag":"span","props":{"class":"line","line":23},"children":[{"type":"element","tag":"span","props":{"style":"--shiki-light:#39ADB5;--shiki-default:#24292E;--shiki-dark:#E1E4E8;--shiki-sepia:#F8F8F2"},"children":[{"type":"text","value":"                    }\n"}]}]},{"type":"element","tag":"span","props":{"class":"line","line":24},"children":[{"type":"element","tag":"span","props":{"style":"--shiki-light:#39ADB5;--shiki-default:#24292E;--shiki-dark:#E1E4E8;--shiki-sepia:#F8F8F2"},"children":[{"type":"text","value":"                }\n"}]}]},{"type":"element","tag":"span","props":{"class":"line","line":25},"children":[{"type":"element","tag":"span","props":{"style":"--shiki-light:#39ADB5;--shiki-default:#24292E;--shiki-dark:#E1E4E8;--shiki-sepia:#F8F8F2"},"children":[{"type":"text","value":"            }\n"}]}]},{"type":"element","tag":"span","props":{"class":"line","line":26},"children":[{"type":"element","tag":"span","props":{"style":"--shiki-light:#39ADB5;--shiki-default:#D73A49;--shiki-dark:#F97583;--shiki-sepia:#F92672;--shiki-light-font-style:italic;--shiki-default-font-style:inherit;--shiki-dark-font-style:inherit;--shiki-sepia-font-style:inherit"},"children":[{"type":"text","value":"            return"}]},{"type":"element","tag":"span","props":{"style":"--shiki-light:#90A4AE;--shiki-default:#24292E;--shiki-dark:#E1E4E8;--shiki-sepia:#F8F8F2"},"children":[{"type":"text","value":" cloned\n"}]}]},{"type":"element","tag":"span","props":{"class":"line","line":27},"children":[{"type":"element","tag":"span","props":{"style":"--shiki-light:#39ADB5;--shiki-default:#24292E;--shiki-dark:#E1E4E8;--shiki-sepia:#F8F8F2"},"children":[{"type":"text","value":"        }\n"}]}]},{"type":"element","tag":"span","props":{"class":"line","line":28},"children":[{"type":"element","tag":"span","props":{"style":"--shiki-light:#39ADB5;--shiki-default:#24292E;--shiki-dark:#E1E4E8;--shiki-sepia:#F8F8F2"},"children":[{"type":"text","value":"    }\n"}]}]},{"type":"element","tag":"span","props":{"class":"line","line":29},"children":[{"type":"element","tag":"span","props":{"style":"--shiki-light:#39ADB5;--shiki-default:#24292E;--shiki-dark:#E1E4E8;--shiki-sepia:#F8F8F2"},"children":[{"type":"text","value":"}"}]},{"type":"element","tag":"span","props":{"style":"--shiki-light:#90A4AE;--shiki-default:#24292E;--shiki-dark:#E1E4E8;--shiki-sepia:#F8F8F2"},"children":[{"type":"text","value":"())\n"}]}]}]}]},{"type":"element","tag":"h2","props":{"id":"extra"},"children":[{"type":"text","value":"Extra"}]},{"type":"element","tag":"p","props":{},"children":[{"type":"text","value":"新规范有了 toSpliced 方法，和 slice 一样是浅拷贝。"}]},{"type":"element","tag":"style","props":{},"children":[{"type":"text","value":"html .light .shiki span {color: var(--shiki-light);background: var(--shiki-light-bg);font-style: var(--shiki-light-font-style);font-weight: var(--shiki-light-font-weight);text-decoration: var(--shiki-light-text-decoration);}html.light .shiki span {color: var(--shiki-light);background: var(--shiki-light-bg);font-style: var(--shiki-light-font-style);font-weight: var(--shiki-light-font-weight);text-decoration: var(--shiki-light-text-decoration);}html .default .shiki span {color: var(--shiki-default);background: var(--shiki-default-bg);font-style: var(--shiki-default-font-style);font-weight: var(--shiki-default-font-weight);text-decoration: var(--shiki-default-text-decoration);}html .shiki span {color: var(--shiki-default);background: var(--shiki-default-bg);font-style: var(--shiki-default-font-style);font-weight: var(--shiki-default-font-weight);text-decoration: var(--shiki-default-text-decoration);}html .dark .shiki span {color: var(--shiki-dark);background: var(--shiki-dark-bg);font-style: var(--shiki-dark-font-style);font-weight: var(--shiki-dark-font-weight);text-decoration: var(--shiki-dark-text-decoration);}html.dark .shiki span {color: var(--shiki-dark);background: var(--shiki-dark-bg);font-style: var(--shiki-dark-font-style);font-weight: var(--shiki-dark-font-weight);text-decoration: var(--shiki-dark-text-decoration);}html .sepia .shiki span {color: var(--shiki-sepia);background: var(--shiki-sepia-bg);font-style: var(--shiki-sepia-font-style);font-weight: var(--shiki-sepia-font-weight);text-decoration: var(--shiki-sepia-text-decoration);}html.sepia .shiki span {color: var(--shiki-sepia);background: var(--shiki-sepia-bg);font-style: var(--shiki-sepia-font-style);font-weight: var(--shiki-sepia-font-weight);text-decoration: var(--shiki-sepia-text-decoration);}"}]}],"toc":{"title":"","searchDepth":2,"depth":2,"links":[{"id":"简介","depth":2,"text":"简介"},{"id":"特殊处理方案","depth":2,"text":"特殊处理方案"},{"id":"改进-arrayprototypeslice","depth":2,"text":"改进 Array.prototype.slice"},{"id":"extra","depth":2,"text":"Extra"}]}},"_type":"markdown","_id":"content:8.source-code:_es:array-slice.md","_source":"content","_file":"8.source-code/_es/array-slice.md","_extension":"md"}