{"_path":"/maps/_frontend/w3c","_dir":"_frontend","_draft":false,"_partial":true,"_locale":"","title":"W3C Standards","description":"","body":{"type":"root","children":[{"type":"element","tag":"h2","props":{"id":"es"},"children":[{"type":"text","value":"ES"}]},{"type":"element","tag":"ul","props":{},"children":[{"type":"element","tag":"li","props":{},"children":[{"type":"element","tag":"a","props":{"href":"/maps/_frontend/w3c/es/proposal-defer-import-eval"},"children":[{"type":"text","value":"proposal-defer-import-eval"}]}]},{"type":"element","tag":"li","props":{},"children":[{"type":"element","tag":"a","props":{"href":"/maps/_frontend/w3c/es/proposal-regexp-v-flag"},"children":[{"type":"text","value":"proposal-regexp-v-flag"}]}]}]},{"type":"element","tag":"h2","props":{"id":"css"},"children":[{"type":"text","value":"CSS"}]},{"type":"element","tag":"ul","props":{},"children":[{"type":"element","tag":"li","props":{},"children":[{"type":"element","tag":"a","props":{"href":"/maps/_frontend/w3c/css/color-module"},"children":[{"type":"text","value":"Color Module"}]}]},{"type":"element","tag":"li","props":{},"children":[{"type":"element","tag":"a","props":{"href":"/maps/_frontend/w3c/css/conditional-rule-module"},"children":[{"type":"text","value":"Conditional Rule Module"}]}]}]},{"type":"element","tag":"h2","props":{"id":"security"},"children":[{"type":"text","value":"Security"}]},{"type":"element","tag":"ul","props":{},"children":[{"type":"element","tag":"li","props":{},"children":[{"type":"element","tag":"a","props":{"href":"/maps/_frontend/w3c/security/subresource-integrity"},"children":[{"type":"text","value":"SubResource Integrity"}]}]}]},{"type":"element","tag":"h2","props":{"id":"web"},"children":[{"type":"text","value":"Web"}]},{"type":"element","tag":"ul","props":{},"children":[{"type":"element","tag":"li","props":{},"children":[{"type":"element","tag":"a","props":{"href":"/maps/_frontend/w3c/screen/multi-screen-window-lacement"},"children":[{"type":"text","value":"Multi-Screen Window Placement"}]}]}]}],"toc":{"title":"","searchDepth":2,"depth":2,"links":[{"id":"es","depth":2,"text":"ES"},{"id":"css","depth":2,"text":"CSS"},{"id":"security","depth":2,"text":"Security"},{"id":"web","depth":2,"text":"Web"}]}},"_type":"markdown","_id":"content:6.maps:_frontend:w3c:0.index.md","_source":"content","_file":"6.maps/_frontend/w3c/0.index.md","_stem":"6.maps/_frontend/w3c/0.index","_extension":"md"}