{"_path":"/maps/_ai/ai","_dir":"_ai","_draft":false,"_partial":true,"_locale":"","title":"AI","description":"","body":{"type":"root","children":[{"type":"element","tag":"h1","props":{"id":"ai"},"children":[{"type":"text","value":"AI"}]},{"type":"element","tag":"h2","props":{"id":"prompt"},"children":[{"type":"text","value":"Prompt"}]},{"type":"element","tag":"ul","props":{},"children":[{"type":"element","tag":"li","props":{},"children":[{"type":"element","tag":"a","props":{"href":"/maps/_ai/prompt/prompt"},"children":[{"type":"text","value":"提示"}]}]}]}],"toc":{"title":"","searchDepth":2,"depth":2,"links":[{"id":"prompt","depth":2,"text":"Prompt"}]}},"_type":"markdown","_id":"content:6.maps:_ai:ai.md","_source":"content","_file":"6.maps/_ai/ai.md","_extension":"md"}