{"_path":"/maps/_ui/ui","_dir":"_ui","_draft":false,"_partial":true,"_locale":"","title":"用户界面（UI）","description":"用户界面（UI）设计是指设计师设计的用户界面，是用户与产品之间的桥梁。用户界面设计是一个复杂的过程，其中包括设计、测试和改进。设计师必须考虑用户的需求、产品的功能和用户界面的外观。用户界面设计是一个交叉学科，涉及心理学、设计、计算机科学和其他领域。","body":{"type":"root","children":[{"type":"element","tag":"h4","props":{"id":"用户交互控件分类"},"children":[{"type":"text","value":"用户交互控件分类？"}]},{"type":"element","tag":"p","props":{},"children":[{"type":"text","value":"见："},{"type":"element","tag":"a","props":{"href":"https://www.nngroup.com/articles/ui-elements-glossary","rel":["nofollow"]},"children":[{"type":"text","value":"User-Interface Elements: Glossary"}]}]}],"toc":{"title":"","searchDepth":2,"depth":2,"links":[]}},"_type":"markdown","_id":"content:6.maps:_ui:ui.md","_source":"content","_file":"6.maps/_ui/ui.md","_stem":"6.maps/_ui/ui","_extension":"md"}