{"_path":"/source-code/_architecture/awade","_dir":"_architecture","_draft":false,"_partial":true,"_locale":"","title":"Awade","description":"中兴的一套低码系统。Jigsaw 是其前端组件库。","body":{"type":"root","children":[{"type":"element","tag":"h2","props":{"id":"问题"},"children":[{"type":"text","value":"问题"}]},{"type":"element","tag":"h4","props":{"id":"代码编译器的实现"},"children":[{"type":"text","value":"代码编译器的实现？"}]},{"type":"element","tag":"p","props":{},"children":[{"type":"text","value":"相较于一个具体的简单的实现了 html、script 结构的 tableCmpt 的 Angular 组件，增加了一层代码编译器抽象，把属性抽象成类，具体的组件实现由 SVD（Structured View Director）指导。"}]},{"type":"element","tag":"pre","props":{"className":"language-typescript shiki shiki-themes material-theme-lighter github-light github-dark monokai","code":"abstract class Property {\n  // 这是一个抽象函数，只有声明，无法实现\n  abstract script(): string;\n  name: string = '';\n  value: string = '';\n  member: string = '';\n  property(): string {\n    // ...\n  }\n}\nabstract class SVD {\n  // 和 Property 类似，基类里不知道如何实现的方法，都只声明，不实现\n  abstract script(): string;\n  properties: Property[];\n  selector: string = '';\n  // 能在基类里实现的方法都尽量在基类提供实现，这样子类直接复用就好了\n  html(): string {\n    // ...\n  }\n}\n","language":"typescript","meta":"","style":""},"children":[{"type":"element","tag":"code","props":{"__ignoreMap":""},"children":[{"type":"element","tag":"span","props":{"class":"line","line":1},"children":[{"type":"element","tag":"span","props":{"style":"--shiki-light:#9C3EDA;--shiki-default:#D73A49;--shiki-dark:#F97583;--shiki-sepia:#F92672"},"children":[{"type":"text","value":"abstract"}]},{"type":"element","tag":"span","props":{"style":"--shiki-light:#9C3EDA;--shiki-light-font-style:inherit;--shiki-default:#D73A49;--shiki-default-font-style:inherit;--shiki-dark:#F97583;--shiki-dark-font-style:inherit;--shiki-sepia:#66D9EF;--shiki-sepia-font-style:italic"},"children":[{"type":"text","value":" class"}]},{"type":"element","tag":"span","props":{"style":"--shiki-light:#E2931D;--shiki-light-text-decoration:inherit;--shiki-default:#6F42C1;--shiki-default-text-decoration:inherit;--shiki-dark:#B392F0;--shiki-dark-text-decoration:inherit;--shiki-sepia:#A6E22E;--shiki-sepia-text-decoration:underline"},"children":[{"type":"text","value":" Property"}]},{"type":"element","tag":"span","props":{"style":"--shiki-light:#39ADB5;--shiki-default:#24292E;--shiki-dark:#E1E4E8;--shiki-sepia:#F8F8F2"},"children":[{"type":"text","value":" {\n"}]}]},{"type":"element","tag":"span","props":{"class":"line","line":2},"children":[{"type":"element","tag":"span","props":{"style":"--shiki-light:#90A4AE;--shiki-light-font-style:italic;--shiki-default:#6A737D;--shiki-default-font-style:inherit;--shiki-dark:#6A737D;--shiki-dark-font-style:inherit;--shiki-sepia:#88846F;--shiki-sepia-font-style:inherit"},"children":[{"type":"text","value":"  // 这是一个抽象函数，只有声明，无法实现\n"}]}]},{"type":"element","tag":"span","props":{"class":"line","line":3},"children":[{"type":"element","tag":"span","props":{"style":"--shiki-light:#9C3EDA;--shiki-default:#D73A49;--shiki-dark:#F97583;--shiki-sepia:#F92672"},"children":[{"type":"text","value":"  abstract"}]},{"type":"element","tag":"span","props":{"style":"--shiki-light:#E53935;--shiki-default:#6F42C1;--shiki-dark:#B392F0;--shiki-sepia:#A6E22E"},"children":[{"type":"text","value":" script"}]},{"type":"element","tag":"span","props":{"style":"--shiki-light:#39ADB5;--shiki-default:#24292E;--shiki-dark:#E1E4E8;--shiki-sepia:#F8F8F2"},"children":[{"type":"text","value":"()"}]},{"type":"element","tag":"span","props":{"style":"--shiki-light:#39ADB5;--shiki-default:#D73A49;--shiki-dark:#F97583;--shiki-sepia:#F92672"},"children":[{"type":"text","value":":"}]},{"type":"element","tag":"span","props":{"style":"--shiki-light:#E2931D;--shiki-light-font-style:inherit;--shiki-default:#005CC5;--shiki-default-font-style:inherit;--shiki-dark:#79B8FF;--shiki-dark-font-style:inherit;--shiki-sepia:#66D9EF;--shiki-sepia-font-style:italic"},"children":[{"type":"text","value":" string"}]},{"type":"element","tag":"span","props":{"style":"--shiki-light:#39ADB5;--shiki-default:#24292E;--shiki-dark:#E1E4E8;--shiki-sepia:#F8F8F2"},"children":[{"type":"text","value":";\n"}]}]},{"type":"element","tag":"span","props":{"class":"line","line":4},"children":[{"type":"element","tag":"span","props":{"style":"--shiki-light:#E53935;--shiki-default:#E36209;--shiki-dark:#FFAB70;--shiki-sepia:#F8F8F2"},"children":[{"type":"text","value":"  name"}]},{"type":"element","tag":"span","props":{"style":"--shiki-light:#39ADB5;--shiki-default:#D73A49;--shiki-dark:#F97583;--shiki-sepia:#F92672"},"children":[{"type":"text","value":":"}]},{"type":"element","tag":"span","props":{"style":"--shiki-light:#E2931D;--shiki-light-font-style:inherit;--shiki-default:#005CC5;--shiki-default-font-style:inherit;--shiki-dark:#79B8FF;--shiki-dark-font-style:inherit;--shiki-sepia:#66D9EF;--shiki-sepia-font-style:italic"},"children":[{"type":"text","value":" string"}]},{"type":"element","tag":"span","props":{"style":"--shiki-light:#39ADB5;--shiki-default:#D73A49;--shiki-dark:#F97583;--shiki-sepia:#F92672"},"children":[{"type":"text","value":" ="}]},{"type":"element","tag":"span","props":{"style":"--shiki-light:#39ADB5;--shiki-default:#032F62;--shiki-dark:#9ECBFF;--shiki-sepia:#E6DB74"},"children":[{"type":"text","value":" ''"}]},{"type":"element","tag":"span","props":{"style":"--shiki-light:#39ADB5;--shiki-default:#24292E;--shiki-dark:#E1E4E8;--shiki-sepia:#F8F8F2"},"children":[{"type":"text","value":";\n"}]}]},{"type":"element","tag":"span","props":{"class":"line","line":5},"children":[{"type":"element","tag":"span","props":{"style":"--shiki-light:#E53935;--shiki-default:#E36209;--shiki-dark:#FFAB70;--shiki-sepia:#F8F8F2"},"children":[{"type":"text","value":"  value"}]},{"type":"element","tag":"span","props":{"style":"--shiki-light:#39ADB5;--shiki-default:#D73A49;--shiki-dark:#F97583;--shiki-sepia:#F92672"},"children":[{"type":"text","value":":"}]},{"type":"element","tag":"span","props":{"style":"--shiki-light:#E2931D;--shiki-light-font-style:inherit;--shiki-default:#005CC5;--shiki-default-font-style:inherit;--shiki-dark:#79B8FF;--shiki-dark-font-style:inherit;--shiki-sepia:#66D9EF;--shiki-sepia-font-style:italic"},"children":[{"type":"text","value":" string"}]},{"type":"element","tag":"span","props":{"style":"--shiki-light:#39ADB5;--shiki-default:#D73A49;--shiki-dark:#F97583;--shiki-sepia:#F92672"},"children":[{"type":"text","value":" ="}]},{"type":"element","tag":"span","props":{"style":"--shiki-light:#39ADB5;--shiki-default:#032F62;--shiki-dark:#9ECBFF;--shiki-sepia:#E6DB74"},"children":[{"type":"text","value":" ''"}]},{"type":"element","tag":"span","props":{"style":"--shiki-light:#39ADB5;--shiki-default:#24292E;--shiki-dark:#E1E4E8;--shiki-sepia:#F8F8F2"},"children":[{"type":"text","value":";\n"}]}]},{"type":"element","tag":"span","props":{"class":"line","line":6},"children":[{"type":"element","tag":"span","props":{"style":"--shiki-light:#E53935;--shiki-default:#E36209;--shiki-dark:#FFAB70;--shiki-sepia:#F8F8F2"},"children":[{"type":"text","value":"  member"}]},{"type":"element","tag":"span","props":{"style":"--shiki-light:#39ADB5;--shiki-default:#D73A49;--shiki-dark:#F97583;--shiki-sepia:#F92672"},"children":[{"type":"text","value":":"}]},{"type":"element","tag":"span","props":{"style":"--shiki-light:#E2931D;--shiki-light-font-style:inherit;--shiki-default:#005CC5;--shiki-default-font-style:inherit;--shiki-dark:#79B8FF;--shiki-dark-font-style:inherit;--shiki-sepia:#66D9EF;--shiki-sepia-font-style:italic"},"children":[{"type":"text","value":" string"}]},{"type":"element","tag":"span","props":{"style":"--shiki-light:#39ADB5;--shiki-default:#D73A49;--shiki-dark:#F97583;--shiki-sepia:#F92672"},"children":[{"type":"text","value":" ="}]},{"type":"element","tag":"span","props":{"style":"--shiki-light:#39ADB5;--shiki-default:#032F62;--shiki-dark:#9ECBFF;--shiki-sepia:#E6DB74"},"children":[{"type":"text","value":" ''"}]},{"type":"element","tag":"span","props":{"style":"--shiki-light:#39ADB5;--shiki-default:#24292E;--shiki-dark:#E1E4E8;--shiki-sepia:#F8F8F2"},"children":[{"type":"text","value":";\n"}]}]},{"type":"element","tag":"span","props":{"class":"line","line":7},"children":[{"type":"element","tag":"span","props":{"style":"--shiki-light:#E53935;--shiki-default:#6F42C1;--shiki-dark:#B392F0;--shiki-sepia:#A6E22E"},"children":[{"type":"text","value":"  property"}]},{"type":"element","tag":"span","props":{"style":"--shiki-light:#39ADB5;--shiki-default:#24292E;--shiki-dark:#E1E4E8;--shiki-sepia:#F8F8F2"},"children":[{"type":"text","value":"()"}]},{"type":"element","tag":"span","props":{"style":"--shiki-light:#39ADB5;--shiki-default:#D73A49;--shiki-dark:#F97583;--shiki-sepia:#F92672"},"children":[{"type":"text","value":":"}]},{"type":"element","tag":"span","props":{"style":"--shiki-light:#E2931D;--shiki-light-font-style:inherit;--shiki-default:#005CC5;--shiki-default-font-style:inherit;--shiki-dark:#79B8FF;--shiki-dark-font-style:inherit;--shiki-sepia:#66D9EF;--shiki-sepia-font-style:italic"},"children":[{"type":"text","value":" string"}]},{"type":"element","tag":"span","props":{"style":"--shiki-light:#39ADB5;--shiki-default:#24292E;--shiki-dark:#E1E4E8;--shiki-sepia:#F8F8F2"},"children":[{"type":"text","value":" {\n"}]}]},{"type":"element","tag":"span","props":{"class":"line","line":8},"children":[{"type":"element","tag":"span","props":{"style":"--shiki-light:#90A4AE;--shiki-light-font-style:italic;--shiki-default:#6A737D;--shiki-default-font-style:inherit;--shiki-dark:#6A737D;--shiki-dark-font-style:inherit;--shiki-sepia:#88846F;--shiki-sepia-font-style:inherit"},"children":[{"type":"text","value":"    // ...\n"}]}]},{"type":"element","tag":"span","props":{"class":"line","line":9},"children":[{"type":"element","tag":"span","props":{"style":"--shiki-light:#39ADB5;--shiki-default:#24292E;--shiki-dark:#E1E4E8;--shiki-sepia:#F8F8F2"},"children":[{"type":"text","value":"  }\n"}]}]},{"type":"element","tag":"span","props":{"class":"line","line":10},"children":[{"type":"element","tag":"span","props":{"style":"--shiki-light:#39ADB5;--shiki-default:#24292E;--shiki-dark:#E1E4E8;--shiki-sepia:#F8F8F2"},"children":[{"type":"text","value":"}\n"}]}]},{"type":"element","tag":"span","props":{"class":"line","line":11},"children":[{"type":"element","tag":"span","props":{"style":"--shiki-light:#9C3EDA;--shiki-default:#D73A49;--shiki-dark:#F97583;--shiki-sepia:#F92672"},"children":[{"type":"text","value":"abstract"}]},{"type":"element","tag":"span","props":{"style":"--shiki-light:#9C3EDA;--shiki-light-font-style:inherit;--shiki-default:#D73A49;--shiki-default-font-style:inherit;--shiki-dark:#F97583;--shiki-dark-font-style:inherit;--shiki-sepia:#66D9EF;--shiki-sepia-font-style:italic"},"children":[{"type":"text","value":" class"}]},{"type":"element","tag":"span","props":{"style":"--shiki-light:#E2931D;--shiki-light-text-decoration:inherit;--shiki-default:#6F42C1;--shiki-default-text-decoration:inherit;--shiki-dark:#B392F0;--shiki-dark-text-decoration:inherit;--shiki-sepia:#A6E22E;--shiki-sepia-text-decoration:underline"},"children":[{"type":"text","value":" SVD"}]},{"type":"element","tag":"span","props":{"style":"--shiki-light:#39ADB5;--shiki-default:#24292E;--shiki-dark:#E1E4E8;--shiki-sepia:#F8F8F2"},"children":[{"type":"text","value":" {\n"}]}]},{"type":"element","tag":"span","props":{"class":"line","line":12},"children":[{"type":"element","tag":"span","props":{"style":"--shiki-light:#90A4AE;--shiki-light-font-style:italic;--shiki-default:#6A737D;--shiki-default-font-style:inherit;--shiki-dark:#6A737D;--shiki-dark-font-style:inherit;--shiki-sepia:#88846F;--shiki-sepia-font-style:inherit"},"children":[{"type":"text","value":"  // 和 Property 类似，基类里不知道如何实现的方法，都只声明，不实现\n"}]}]},{"type":"element","tag":"span","props":{"class":"line","line":13},"children":[{"type":"element","tag":"span","props":{"style":"--shiki-light:#9C3EDA;--shiki-default:#D73A49;--shiki-dark:#F97583;--shiki-sepia:#F92672"},"children":[{"type":"text","value":"  abstract"}]},{"type":"element","tag":"span","props":{"style":"--shiki-light:#E53935;--shiki-default:#6F42C1;--shiki-dark:#B392F0;--shiki-sepia:#A6E22E"},"children":[{"type":"text","value":" script"}]},{"type":"element","tag":"span","props":{"style":"--shiki-light:#39ADB5;--shiki-default:#24292E;--shiki-dark:#E1E4E8;--shiki-sepia:#F8F8F2"},"children":[{"type":"text","value":"()"}]},{"type":"element","tag":"span","props":{"style":"--shiki-light:#39ADB5;--shiki-default:#D73A49;--shiki-dark:#F97583;--shiki-sepia:#F92672"},"children":[{"type":"text","value":":"}]},{"type":"element","tag":"span","props":{"style":"--shiki-light:#E2931D;--shiki-light-font-style:inherit;--shiki-default:#005CC5;--shiki-default-font-style:inherit;--shiki-dark:#79B8FF;--shiki-dark-font-style:inherit;--shiki-sepia:#66D9EF;--shiki-sepia-font-style:italic"},"children":[{"type":"text","value":" string"}]},{"type":"element","tag":"span","props":{"style":"--shiki-light:#39ADB5;--shiki-default:#24292E;--shiki-dark:#E1E4E8;--shiki-sepia:#F8F8F2"},"children":[{"type":"text","value":";\n"}]}]},{"type":"element","tag":"span","props":{"class":"line","line":14},"children":[{"type":"element","tag":"span","props":{"style":"--shiki-light:#E53935;--shiki-default:#E36209;--shiki-dark:#FFAB70;--shiki-sepia:#F8F8F2"},"children":[{"type":"text","value":"  properties"}]},{"type":"element","tag":"span","props":{"style":"--shiki-light:#39ADB5;--shiki-default:#D73A49;--shiki-dark:#F97583;--shiki-sepia:#F92672"},"children":[{"type":"text","value":":"}]},{"type":"element","tag":"span","props":{"style":"--shiki-light:#E2931D;--shiki-light-text-decoration:inherit;--shiki-default:#6F42C1;--shiki-default-text-decoration:inherit;--shiki-dark:#B392F0;--shiki-dark-text-decoration:inherit;--shiki-sepia:#A6E22E;--shiki-sepia-text-decoration:underline"},"children":[{"type":"text","value":" Property"}]},{"type":"element","tag":"span","props":{"style":"--shiki-light:#90A4AE;--shiki-default:#24292E;--shiki-dark:#E1E4E8;--shiki-sepia:#F8F8F2"},"children":[{"type":"text","value":"[]"}]},{"type":"element","tag":"span","props":{"style":"--shiki-light:#39ADB5;--shiki-default:#24292E;--shiki-dark:#E1E4E8;--shiki-sepia:#F8F8F2"},"children":[{"type":"text","value":";\n"}]}]},{"type":"element","tag":"span","props":{"class":"line","line":15},"children":[{"type":"element","tag":"span","props":{"style":"--shiki-light:#E53935;--shiki-default:#E36209;--shiki-dark:#FFAB70;--shiki-sepia:#F8F8F2"},"children":[{"type":"text","value":"  selector"}]},{"type":"element","tag":"span","props":{"style":"--shiki-light:#39ADB5;--shiki-default:#D73A49;--shiki-dark:#F97583;--shiki-sepia:#F92672"},"children":[{"type":"text","value":":"}]},{"type":"element","tag":"span","props":{"style":"--shiki-light:#E2931D;--shiki-light-font-style:inherit;--shiki-default:#005CC5;--shiki-default-font-style:inherit;--shiki-dark:#79B8FF;--shiki-dark-font-style:inherit;--shiki-sepia:#66D9EF;--shiki-sepia-font-style:italic"},"children":[{"type":"text","value":" string"}]},{"type":"element","tag":"span","props":{"style":"--shiki-light:#39ADB5;--shiki-default:#D73A49;--shiki-dark:#F97583;--shiki-sepia:#F92672"},"children":[{"type":"text","value":" ="}]},{"type":"element","tag":"span","props":{"style":"--shiki-light:#39ADB5;--shiki-default:#032F62;--shiki-dark:#9ECBFF;--shiki-sepia:#E6DB74"},"children":[{"type":"text","value":" ''"}]},{"type":"element","tag":"span","props":{"style":"--shiki-light:#39ADB5;--shiki-default:#24292E;--shiki-dark:#E1E4E8;--shiki-sepia:#F8F8F2"},"children":[{"type":"text","value":";\n"}]}]},{"type":"element","tag":"span","props":{"class":"line","line":16},"children":[{"type":"element","tag":"span","props":{"style":"--shiki-light:#90A4AE;--shiki-light-font-style:italic;--shiki-default:#6A737D;--shiki-default-font-style:inherit;--shiki-dark:#6A737D;--shiki-dark-font-style:inherit;--shiki-sepia:#88846F;--shiki-sepia-font-style:inherit"},"children":[{"type":"text","value":"  // 能在基类里实现的方法都尽量在基类提供实现，这样子类直接复用就好了\n"}]}]},{"type":"element","tag":"span","props":{"class":"line","line":17},"children":[{"type":"element","tag":"span","props":{"style":"--shiki-light:#E53935;--shiki-default:#6F42C1;--shiki-dark:#B392F0;--shiki-sepia:#A6E22E"},"children":[{"type":"text","value":"  html"}]},{"type":"element","tag":"span","props":{"style":"--shiki-light:#39ADB5;--shiki-default:#24292E;--shiki-dark:#E1E4E8;--shiki-sepia:#F8F8F2"},"children":[{"type":"text","value":"()"}]},{"type":"element","tag":"span","props":{"style":"--shiki-light:#39ADB5;--shiki-default:#D73A49;--shiki-dark:#F97583;--shiki-sepia:#F92672"},"children":[{"type":"text","value":":"}]},{"type":"element","tag":"span","props":{"style":"--shiki-light:#E2931D;--shiki-light-font-style:inherit;--shiki-default:#005CC5;--shiki-default-font-style:inherit;--shiki-dark:#79B8FF;--shiki-dark-font-style:inherit;--shiki-sepia:#66D9EF;--shiki-sepia-font-style:italic"},"children":[{"type":"text","value":" string"}]},{"type":"element","tag":"span","props":{"style":"--shiki-light:#39ADB5;--shiki-default:#24292E;--shiki-dark:#E1E4E8;--shiki-sepia:#F8F8F2"},"children":[{"type":"text","value":" {\n"}]}]},{"type":"element","tag":"span","props":{"class":"line","line":18},"children":[{"type":"element","tag":"span","props":{"style":"--shiki-light:#90A4AE;--shiki-light-font-style:italic;--shiki-default:#6A737D;--shiki-default-font-style:inherit;--shiki-dark:#6A737D;--shiki-dark-font-style:inherit;--shiki-sepia:#88846F;--shiki-sepia-font-style:inherit"},"children":[{"type":"text","value":"    // ...\n"}]}]},{"type":"element","tag":"span","props":{"class":"line","line":19},"children":[{"type":"element","tag":"span","props":{"style":"--shiki-light:#39ADB5;--shiki-default:#24292E;--shiki-dark:#E1E4E8;--shiki-sepia:#F8F8F2"},"children":[{"type":"text","value":"  }\n"}]}]},{"type":"element","tag":"span","props":{"class":"line","line":20},"children":[{"type":"element","tag":"span","props":{"style":"--shiki-light:#39ADB5;--shiki-default:#24292E;--shiki-dark:#E1E4E8;--shiki-sepia:#F8F8F2"},"children":[{"type":"text","value":"}\n"}]}]}]}]},{"type":"element","tag":"p","props":{},"children":[{"type":"text","value":"任何要纳入到低代码平台的组件都需要继承这些基类，才能派生出描述具体某个组件如何使用的子类。"}]},{"type":"element","tag":"pre","props":{"className":"language-typescript shiki shiki-themes material-theme-lighter github-light github-dark monokai","code":"class JigsawSelect extends SVD {\n  properties: Property[] = [\n    new DataProperty(), new ValueProperty()\n  ];\n  selector = 'jigsaw-select';\n  script() {\n    // ...\n  }\n}\n","language":"typescript","meta":"","style":""},"children":[{"type":"element","tag":"code","props":{"__ignoreMap":""},"children":[{"type":"element","tag":"span","props":{"class":"line","line":1},"children":[{"type":"element","tag":"span","props":{"style":"--shiki-light:#9C3EDA;--shiki-light-font-style:inherit;--shiki-default:#D73A49;--shiki-default-font-style:inherit;--shiki-dark:#F97583;--shiki-dark-font-style:inherit;--shiki-sepia:#66D9EF;--shiki-sepia-font-style:italic"},"children":[{"type":"text","value":"class"}]},{"type":"element","tag":"span","props":{"style":"--shiki-light:#E2931D;--shiki-light-text-decoration:inherit;--shiki-default:#6F42C1;--shiki-default-text-decoration:inherit;--shiki-dark:#B392F0;--shiki-dark-text-decoration:inherit;--shiki-sepia:#A6E22E;--shiki-sepia-text-decoration:underline"},"children":[{"type":"text","value":" JigsawSelect"}]},{"type":"element","tag":"span","props":{"style":"--shiki-light:#9C3EDA;--shiki-default:#D73A49;--shiki-dark:#F97583;--shiki-sepia:#F92672"},"children":[{"type":"text","value":" extends"}]},{"type":"element","tag":"span","props":{"style":"--shiki-light:#E2931D;--shiki-light-font-style:inherit;--shiki-light-text-decoration:inherit;--shiki-default:#6F42C1;--shiki-default-font-style:inherit;--shiki-default-text-decoration:inherit;--shiki-dark:#B392F0;--shiki-dark-font-style:inherit;--shiki-dark-text-decoration:inherit;--shiki-sepia:#A6E22E;--shiki-sepia-font-style:italic;--shiki-sepia-text-decoration:underline"},"children":[{"type":"text","value":" SVD"}]},{"type":"element","tag":"span","props":{"style":"--shiki-light:#39ADB5;--shiki-default:#24292E;--shiki-dark:#E1E4E8;--shiki-sepia:#F8F8F2"},"children":[{"type":"text","value":" {\n"}]}]},{"type":"element","tag":"span","props":{"class":"line","line":2},"children":[{"type":"element","tag":"span","props":{"style":"--shiki-light:#E53935;--shiki-default:#E36209;--shiki-dark:#FFAB70;--shiki-sepia:#F8F8F2"},"children":[{"type":"text","value":"  properties"}]},{"type":"element","tag":"span","props":{"style":"--shiki-light:#39ADB5;--shiki-default:#D73A49;--shiki-dark:#F97583;--shiki-sepia:#F92672"},"children":[{"type":"text","value":":"}]},{"type":"element","tag":"span","props":{"style":"--shiki-light:#E2931D;--shiki-light-text-decoration:inherit;--shiki-default:#6F42C1;--shiki-default-text-decoration:inherit;--shiki-dark:#B392F0;--shiki-dark-text-decoration:inherit;--shiki-sepia:#A6E22E;--shiki-sepia-text-decoration:underline"},"children":[{"type":"text","value":" Property"}]},{"type":"element","tag":"span","props":{"style":"--shiki-light:#90A4AE;--shiki-default:#24292E;--shiki-dark:#E1E4E8;--shiki-sepia:#F8F8F2"},"children":[{"type":"text","value":"[] "}]},{"type":"element","tag":"span","props":{"style":"--shiki-light:#39ADB5;--shiki-default:#D73A49;--shiki-dark:#F97583;--shiki-sepia:#F92672"},"children":[{"type":"text","value":"="}]},{"type":"element","tag":"span","props":{"style":"--shiki-light:#90A4AE;--shiki-default:#24292E;--shiki-dark:#E1E4E8;--shiki-sepia:#F8F8F2"},"children":[{"type":"text","value":" [\n"}]}]},{"type":"element","tag":"span","props":{"class":"line","line":3},"children":[{"type":"element","tag":"span","props":{"style":"--shiki-light:#39ADB5;--shiki-default:#D73A49;--shiki-dark:#F97583;--shiki-sepia:#F92672"},"children":[{"type":"text","value":"    new"}]},{"type":"element","tag":"span","props":{"style":"--shiki-light:#E53935;--shiki-default:#6F42C1;--shiki-dark:#B392F0;--shiki-sepia:#A6E22E"},"children":[{"type":"text","value":" DataProperty"}]},{"type":"element","tag":"span","props":{"style":"--shiki-light:#90A4AE;--shiki-default:#24292E;--shiki-dark:#E1E4E8;--shiki-sepia:#F8F8F2"},"children":[{"type":"text","value":"()"}]},{"type":"element","tag":"span","props":{"style":"--shiki-light:#39ADB5;--shiki-default:#24292E;--shiki-dark:#E1E4E8;--shiki-sepia:#F8F8F2"},"children":[{"type":"text","value":","}]},{"type":"element","tag":"span","props":{"style":"--shiki-light:#39ADB5;--shiki-default:#D73A49;--shiki-dark:#F97583;--shiki-sepia:#F92672"},"children":[{"type":"text","value":" new"}]},{"type":"element","tag":"span","props":{"style":"--shiki-light:#E53935;--shiki-default:#6F42C1;--shiki-dark:#B392F0;--shiki-sepia:#A6E22E"},"children":[{"type":"text","value":" ValueProperty"}]},{"type":"element","tag":"span","props":{"style":"--shiki-light:#90A4AE;--shiki-default:#24292E;--shiki-dark:#E1E4E8;--shiki-sepia:#F8F8F2"},"children":[{"type":"text","value":"()\n"}]}]},{"type":"element","tag":"span","props":{"class":"line","line":4},"children":[{"type":"element","tag":"span","props":{"style":"--shiki-light:#90A4AE;--shiki-default:#24292E;--shiki-dark:#E1E4E8;--shiki-sepia:#F8F8F2"},"children":[{"type":"text","value":"  ]"}]},{"type":"element","tag":"span","props":{"style":"--shiki-light:#39ADB5;--shiki-default:#24292E;--shiki-dark:#E1E4E8;--shiki-sepia:#F8F8F2"},"children":[{"type":"text","value":";\n"}]}]},{"type":"element","tag":"span","props":{"class":"line","line":5},"children":[{"type":"element","tag":"span","props":{"style":"--shiki-light:#E53935;--shiki-default:#E36209;--shiki-dark:#FFAB70;--shiki-sepia:#F8F8F2"},"children":[{"type":"text","value":"  selector"}]},{"type":"element","tag":"span","props":{"style":"--shiki-light:#39ADB5;--shiki-default:#D73A49;--shiki-dark:#F97583;--shiki-sepia:#F92672"},"children":[{"type":"text","value":" ="}]},{"type":"element","tag":"span","props":{"style":"--shiki-light:#39ADB5;--shiki-default:#032F62;--shiki-dark:#9ECBFF;--shiki-sepia:#E6DB74"},"children":[{"type":"text","value":" '"}]},{"type":"element","tag":"span","props":{"style":"--shiki-light:#91B859;--shiki-default:#032F62;--shiki-dark:#9ECBFF;--shiki-sepia:#E6DB74"},"children":[{"type":"text","value":"jigsaw-select"}]},{"type":"element","tag":"span","props":{"style":"--shiki-light:#39ADB5;--shiki-default:#032F62;--shiki-dark:#9ECBFF;--shiki-sepia:#E6DB74"},"children":[{"type":"text","value":"'"}]},{"type":"element","tag":"span","props":{"style":"--shiki-light:#39ADB5;--shiki-default:#24292E;--shiki-dark:#E1E4E8;--shiki-sepia:#F8F8F2"},"children":[{"type":"text","value":";\n"}]}]},{"type":"element","tag":"span","props":{"class":"line","line":6},"children":[{"type":"element","tag":"span","props":{"style":"--shiki-light:#E53935;--shiki-default:#6F42C1;--shiki-dark:#B392F0;--shiki-sepia:#A6E22E"},"children":[{"type":"text","value":"  script"}]},{"type":"element","tag":"span","props":{"style":"--shiki-light:#39ADB5;--shiki-default:#24292E;--shiki-dark:#E1E4E8;--shiki-sepia:#F8F8F2"},"children":[{"type":"text","value":"()"}]},{"type":"element","tag":"span","props":{"style":"--shiki-light:#39ADB5;--shiki-default:#24292E;--shiki-dark:#E1E4E8;--shiki-sepia:#F8F8F2"},"children":[{"type":"text","value":" {\n"}]}]},{"type":"element","tag":"span","props":{"class":"line","line":7},"children":[{"type":"element","tag":"span","props":{"style":"--shiki-light:#90A4AE;--shiki-light-font-style:italic;--shiki-default:#6A737D;--shiki-default-font-style:inherit;--shiki-dark:#6A737D;--shiki-dark-font-style:inherit;--shiki-sepia:#88846F;--shiki-sepia-font-style:inherit"},"children":[{"type":"text","value":"    // ...\n"}]}]},{"type":"element","tag":"span","props":{"class":"line","line":8},"children":[{"type":"element","tag":"span","props":{"style":"--shiki-light:#39ADB5;--shiki-default:#24292E;--shiki-dark:#E1E4E8;--shiki-sepia:#F8F8F2"},"children":[{"type":"text","value":"  }\n"}]}]},{"type":"element","tag":"span","props":{"class":"line","line":9},"children":[{"type":"element","tag":"span","props":{"style":"--shiki-light:#39ADB5;--shiki-default:#24292E;--shiki-dark:#E1E4E8;--shiki-sepia:#F8F8F2"},"children":[{"type":"text","value":"}\n"}]}]}]}]},{"type":"element","tag":"p","props":{},"children":[{"type":"text","value":"Jigsaw 将编辑器插件视为组件+根据协议指导组件生成组件代码的工具。"}]},{"type":"element","tag":"p","props":{},"children":[{"type":"element","tag":"img","props":{"alt":"内置组件集的和插件提供的组件是平起平坐的","src":"https://mgear-image.oss-cn-shanghai.aliyuncs.com/image/other/202503200044256.png?w=50"},"children":[]}]},{"type":"element","tag":"p","props":{},"children":[{"type":"text","value":"作为对比，PRay 的架构要简化很多："}]},{"type":"element","tag":"mermaid","props":{"size":"md"},"children":[{"type":"text","value":"\ngraph TD\n    subgraph InnerCmpts[内置组件库]\n        IButton[按钮]\n        IOther[其他组件]\n    end\n    subgraph ExtCmpts[扩展组件库]\n        EButton[按钮]\n        EOther[其他组件]\n    end\n    Renderer --> VueSchema[Vue-like Schema（props、emits、inject...）]\n    Editor --> Renderer\n    VueSchema --> Vue\n    InnerCmpts --> Vue\n    ExtCmpts --> Vue\n"}]},{"type":"element","tag":"p","props":{},"children":[{"type":"text","value":"其中，代码生成器是一层很薄的动态组件封装，即："}]},{"type":"element","tag":"pre","props":{"className":"language-vue shiki shiki-themes material-theme-lighter github-light github-dark monokai","code":"<component :is=\"xxx\" v-bind=\"props\" v-on=\"events\" />\n","language":"vue","meta":"","style":""},"children":[{"type":"element","tag":"code","props":{"__ignoreMap":""},"children":[{"type":"element","tag":"span","props":{"class":"line","line":1},"children":[{"type":"element","tag":"span","props":{"style":"--shiki-light:#39ADB5;--shiki-default:#24292E;--shiki-dark:#E1E4E8;--shiki-sepia:#F8F8F2"},"children":[{"type":"text","value":"<"}]},{"type":"element","tag":"span","props":{"style":"--shiki-light:#E53935;--shiki-default:#22863A;--shiki-dark:#85E89D;--shiki-sepia:#F92672"},"children":[{"type":"text","value":"component"}]},{"type":"element","tag":"span","props":{"style":"--shiki-light:#39ADB5;--shiki-default:#24292E;--shiki-dark:#E1E4E8;--shiki-sepia:#F8F8F2"},"children":[{"type":"text","value":" :"}]},{"type":"element","tag":"span","props":{"style":"--shiki-light:#9C3EDA;--shiki-default:#6F42C1;--shiki-dark:#B392F0;--shiki-sepia:#A6E22E"},"children":[{"type":"text","value":"is"}]},{"type":"element","tag":"span","props":{"style":"--shiki-light:#39ADB5;--shiki-default:#24292E;--shiki-dark:#E1E4E8;--shiki-sepia:#F8F8F2"},"children":[{"type":"text","value":"="}]},{"type":"element","tag":"span","props":{"style":"--shiki-light:#39ADB5;--shiki-default:#032F62;--shiki-dark:#9ECBFF;--shiki-sepia:#F8F8F2"},"children":[{"type":"text","value":"\""}]},{"type":"element","tag":"span","props":{"style":"--shiki-light:#90A4AE;--shiki-default:#24292E;--shiki-dark:#E1E4E8;--shiki-sepia:#F8F8F2"},"children":[{"type":"text","value":"xxx"}]},{"type":"element","tag":"span","props":{"style":"--shiki-light:#39ADB5;--shiki-default:#032F62;--shiki-dark:#9ECBFF;--shiki-sepia:#F8F8F2"},"children":[{"type":"text","value":"\""}]},{"type":"element","tag":"span","props":{"style":"--shiki-light:#9C3EDA;--shiki-default:#6F42C1;--shiki-dark:#B392F0;--shiki-sepia:#A6E22E"},"children":[{"type":"text","value":" v-bind"}]},{"type":"element","tag":"span","props":{"style":"--shiki-light:#39ADB5;--shiki-default:#24292E;--shiki-dark:#E1E4E8;--shiki-sepia:#F8F8F2"},"children":[{"type":"text","value":"="}]},{"type":"element","tag":"span","props":{"style":"--shiki-light:#39ADB5;--shiki-default:#032F62;--shiki-dark:#9ECBFF;--shiki-sepia:#F8F8F2"},"children":[{"type":"text","value":"\""}]},{"type":"element","tag":"span","props":{"style":"--shiki-light:#90A4AE;--shiki-default:#24292E;--shiki-dark:#E1E4E8;--shiki-sepia:#F8F8F2"},"children":[{"type":"text","value":"props"}]},{"type":"element","tag":"span","props":{"style":"--shiki-light:#39ADB5;--shiki-default:#032F62;--shiki-dark:#9ECBFF;--shiki-sepia:#F8F8F2"},"children":[{"type":"text","value":"\""}]},{"type":"element","tag":"span","props":{"style":"--shiki-light:#9C3EDA;--shiki-default:#6F42C1;--shiki-dark:#B392F0;--shiki-sepia:#A6E22E"},"children":[{"type":"text","value":" v-on"}]},{"type":"element","tag":"span","props":{"style":"--shiki-light:#39ADB5;--shiki-default:#24292E;--shiki-dark:#E1E4E8;--shiki-sepia:#F8F8F2"},"children":[{"type":"text","value":"="}]},{"type":"element","tag":"span","props":{"style":"--shiki-light:#39ADB5;--shiki-default:#032F62;--shiki-dark:#9ECBFF;--shiki-sepia:#F8F8F2"},"children":[{"type":"text","value":"\""}]},{"type":"element","tag":"span","props":{"style":"--shiki-light:#90A4AE;--shiki-default:#24292E;--shiki-dark:#E1E4E8;--shiki-sepia:#F8F8F2"},"children":[{"type":"text","value":"events"}]},{"type":"element","tag":"span","props":{"style":"--shiki-light:#39ADB5;--shiki-default:#032F62;--shiki-dark:#9ECBFF;--shiki-sepia:#F8F8F2"},"children":[{"type":"text","value":"\""}]},{"type":"element","tag":"span","props":{"style":"--shiki-light:#39ADB5;--shiki-default:#24292E;--shiki-dark:#E1E4E8;--shiki-sepia:#F8F8F2"},"children":[{"type":"text","value":" />\n"}]}]}]}]},{"type":"element","tag":"h2","props":{"id":"阅读"},"children":[{"type":"text","value":"阅读"}]},{"type":"element","tag":"ul","props":{},"children":[{"type":"element","tag":"li","props":{},"children":[{"type":"element","tag":"a","props":{"href":"https://time.geekbang.org/column/intro/100108401","rel":["nofollow"]},"children":[{"type":"text","value":"说透低代码 @陈旭"}]}]}]},{"type":"element","tag":"style","props":{},"children":[{"type":"text","value":"html .light .shiki span {color: var(--shiki-light);background: var(--shiki-light-bg);font-style: var(--shiki-light-font-style);font-weight: var(--shiki-light-font-weight);text-decoration: var(--shiki-light-text-decoration);}html.light .shiki span {color: var(--shiki-light);background: var(--shiki-light-bg);font-style: var(--shiki-light-font-style);font-weight: var(--shiki-light-font-weight);text-decoration: var(--shiki-light-text-decoration);}html .default .shiki span {color: var(--shiki-default);background: var(--shiki-default-bg);font-style: var(--shiki-default-font-style);font-weight: var(--shiki-default-font-weight);text-decoration: var(--shiki-default-text-decoration);}html .shiki span {color: var(--shiki-default);background: var(--shiki-default-bg);font-style: var(--shiki-default-font-style);font-weight: var(--shiki-default-font-weight);text-decoration: var(--shiki-default-text-decoration);}html .dark .shiki span {color: var(--shiki-dark);background: var(--shiki-dark-bg);font-style: var(--shiki-dark-font-style);font-weight: var(--shiki-dark-font-weight);text-decoration: var(--shiki-dark-text-decoration);}html.dark .shiki span {color: var(--shiki-dark);background: var(--shiki-dark-bg);font-style: var(--shiki-dark-font-style);font-weight: var(--shiki-dark-font-weight);text-decoration: var(--shiki-dark-text-decoration);}html .sepia .shiki span {color: var(--shiki-sepia);background: var(--shiki-sepia-bg);font-style: var(--shiki-sepia-font-style);font-weight: var(--shiki-sepia-font-weight);text-decoration: var(--shiki-sepia-text-decoration);}html.sepia .shiki span {color: var(--shiki-sepia);background: var(--shiki-sepia-bg);font-style: var(--shiki-sepia-font-style);font-weight: var(--shiki-sepia-font-weight);text-decoration: var(--shiki-sepia-text-decoration);}"}]}],"toc":{"title":"","searchDepth":2,"depth":2,"links":[{"id":"问题","depth":2,"text":"问题"},{"id":"阅读","depth":2,"text":"阅读"}]}},"_type":"markdown","_id":"content:8.source-code:_architecture:awade.md","_source":"content","_file":"8.source-code/_architecture/awade.md","_stem":"8.source-code/_architecture/awade","_extension":"md"}