{"_path":"/maps/_person/galileo","_dir":"_person","_draft":false,"_partial":true,"_locale":"","title":"伽利略·伽利雷","description":"","body":{"type":"root","children":[{"type":"element","tag":"h1","props":{"id":"伽利略伽利雷"},"children":[{"type":"text","value":"伽利略·伽利雷"}]},{"type":"element","tag":"h2","props":{"id":"日心说"},"children":[{"type":"text","value":"日心说"}]}],"toc":{"title":"","searchDepth":2,"depth":2,"links":[{"id":"日心说","depth":2,"text":"日心说"}]}},"_type":"markdown","_id":"content:6.maps:_person:galileo.md","_source":"content","_file":"6.maps/_person/galileo.md","_extension":"md"}