{"nodes": [{"id": "vitest_config_ts", "label": "vitest.config.ts", "file_type": "code", "source_file": "vitest.config.ts", "source_location": "L1"}, {"id": "vitest_config_resolveid", "label": "resolveId()", "file_type": "code", "source_file": "vitest.config.ts", "source_location": "L11"}, {"id": "vitest_config_load", "label": "load()", "file_type": "code", "source_file": "vitest.config.ts", "source_location": "L16"}], "edges": [{"source": "vitest_config_ts", "target": "config", "relation": "imports_from", "confidence": "EXTRACTED", "source_file": "vitest.config.ts", "source_location": "L1", "weight": 1.0}, {"source": "vitest_config_ts", "target": "vitest_config_resolveid", "relation": "contains", "confidence": "EXTRACTED", "source_file": "vitest.config.ts", "source_location": "L11", "weight": 1.0}, {"source": "vitest_config_ts", "target": "vitest_config_load", "relation": "contains", "confidence": "EXTRACTED", "source_file": "vitest.config.ts", "source_location": "L16", "weight": 1.0}]}