{"nodes": [{"id": "product_manager", "label": "Product Manager", "file_type": "document", "source_file": "content/6.maps/_product/product-manager/product-manager.md", "source_location": null, "source_url": null, "captured_at": null, "author": null, "contributor": null}], "edges": [{"source": "product_manager", "target": "user_research", "relation": "conceptually_related_to", "confidence": "INFERRED", "confidence_score": 0.8, "source_file": "content/6.maps/_product/product-manager/product-manager.md", "source_location": null, "weight": 1.0}], "hyperedges": []}