{"nodes": [{"id": "w3c_proposal_defer_import_eval", "label": "proposal-defer-import-eval", "file_type": "document", "source_file": "content/6.maps/_frontend/w3c/es/proposal-defer-import-eval.md", "source_location": null, "source_url": "https://github.com/tc39/proposal-defer-import-eval", "captured_at": null, "author": null, "contributor": null}, {"id": "rationale_defer_import_eval", "label": "\u5ef6\u8fdf\u5bfc\u5165\u6267\u884c\u63d0\u6848\u7684\u52a8\u673a", "file_type": "document", "source_file": "content/6.maps/_frontend/w3c/es/proposal-defer-import-eval.md", "source_location": null, "source_url": "https://github.com/tc39/proposal-defer-import-eval", "captured_at": null, "author": null, "contributor": null}], "edges": [{"source": "rationale_defer_import_eval", "target": "w3c_proposal_defer_import_eval", "relation": "rationale_for", "confidence": "EXTRACTED", "confidence_score": 1.0, "source_file": "content/6.maps/_frontend/w3c/es/proposal-defer-import-eval.md", "source_location": null, "weight": 1.0}, {"source": "w3c_proposal_defer_import_eval", "target": "javascript_promise", "relation": "semantically_similar_to", "confidence": "INFERRED", "confidence_score": 0.75, "source_file": "content/6.maps/_frontend/w3c/es/proposal-defer-import-eval.md", "source_location": null, "weight": 1.0}], "hyperedges": []}