{"nodes": [{"id": "nuxt-ui-v3", "label": "Nuxt UI v3", "file_type": "document", "source_file": "content/8.source-code/_js/nuxt-ui-v3.md", "captured_at": "2026-04-13", "author": "\u4eff\u751f\u72ee\u5b50", "title": "Nuxt UI v3", "description": "Nuxt UI v3"}], "edges": [{"source": "nuxt-ui-v3", "target": "reka-ui", "relation": "depends_on", "confidence": "INFERRED", "confidence_score": 0.7, "source_file": "content/8.source-code/_js/nuxt-ui-v3.md", "source_location": "Nuxt UI powered by Reka UI"}], "hyperedges": []}